{
    "info": {
        "address1": "9348 Civic Center Drive",
        "city": "Beverly Hills",
        "state": "CA",
        "zip": "90210",
        "country": "United States",
        "phone": "310 867 7000",
        "website": "https://www.livenationentertainment.com",
        "industry": "Entertainment",
        "industryKey": "entertainment",
        "industryDisp": "Entertainment",
        "sector": "Communication Services",
        "sectorKey": "communication-services",
        "sectorDisp": "Communication Services",
        "longBusinessSummary": "Live Nation Entertainment, Inc. operates as a live entertainment company worldwide. It operates through Concerts, Ticketing, and Sponsorship & Advertising segments. The Concerts segment promotes live music events in its owned or operated venues, and in rented third-party venues. This segment operates and manages music venues; produces music festivals; creates associated content; and offers management and other services to artists. The Ticketing segment manages the ticketing operations, including the provision of ticketing software and services to consumers with marketplace for tickets and event information through mobile apps, other websites, and retail outlets, as well as its websites, such as livenation.com and ticketmaster.com; and provides ticket resale services. This segment offers ticketing services for arenas, stadiums, amphitheaters, music clubs, concert promoters, professional sports franchises and leagues, college sports teams, performing arts venues, museums, and theaters. The Sponsorship & Advertising segment sells international, national, and local sponsorships and placement of advertising, including signage, online advertising, and promotional programs; rich media offering, including advertising related with live streaming and music-related content; and ads through distribution network of venues, events, and websites. This segment also manages the development of strategic sponsorship programs, as well as develops, books, and produces custom events or programs for specific brands. It owns, operates, or leases entertainment venues. The company was formerly known as Live Nation, Inc. and changed its name to Live Nation Entertainment, Inc. in January 2010. Live Nation Entertainment, Inc. was incorporated in 2005 and is based in Beverly Hills, California.",
        "fullTimeEmployees": 16200,
        "companyOfficers": [
            {
                "maxAge": 1,
                "name": "Mr. Michael  Rapino",
                "age": 58,
                "title": "President, CEO & Director",
                "yearBorn": 1966,
                "fiscalYear": 2024,
                "totalPay": 23161180,
                "exercisedValue": 10813885,
                "unexercisedValue": 50711844
            },
            {
                "maxAge": 1,
                "name": "Mr. Joe  Berchtold",
                "age": 59,
                "title": "President & CFO",
                "yearBorn": 1965,
                "fiscalYear": 2024,
                "totalPay": 6423972,
                "exercisedValue": 3201048,
                "unexercisedValue": 24253456
            },
            {
                "maxAge": 1,
                "name": "Mr. Brian J. Capo",
                "age": 57,
                "title": "Chief Accounting Officer & Senior VP",
                "yearBorn": 1967,
                "fiscalYear": 2024,
                "totalPay": 675000,
                "exercisedValue": 356400,
                "unexercisedValue": 0
            },
            {
                "maxAge": 1,
                "name": "Mr. Michael G. Rowles",
                "age": 58,
                "title": "Executive VP, General Counsel & Secretary",
                "yearBorn": 1966,
                "fiscalYear": 2024,
                "totalPay": 2781954,
                "exercisedValue": 2543860,
                "unexercisedValue": 18564864
            },
            {
                "maxAge": 1,
                "name": "Mr. John  Hopmans",
                "age": 65,
                "title": "Executive Vice President of Mergers & Acquisitions and Strategic Finance",
                "yearBorn": 1959,
                "fiscalYear": 2024,
                "totalPay": 3012980,
                "exercisedValue": 0,
                "unexercisedValue": 33220912
            },
            {
                "maxAge": 1,
                "name": "Ms. Amy  Yong",
                "title": "Senior Vice President of Investor Relations",
                "fiscalYear": 2024,
                "exercisedValue": 0,
                "unexercisedValue": 0
            },
            {
                "maxAge": 1,
                "name": "Ms. Kaitlyn  Henrich",
                "age": 33,
                "title": "Senior Vice President of Corporate Affairs, Corporate Communications & Social Impact",
                "yearBorn": 1991,
                "fiscalYear": 2024,
                "exercisedValue": 0,
                "unexercisedValue": 0
            },
            {
                "maxAge": 1,
                "name": "Ms. Liz  Dyer",
                "age": 38,
                "title": "Senior Vice President of Human Resources",
                "yearBorn": 1986,
                "fiscalYear": 2024,
                "exercisedValue": 0,
                "unexercisedValue": 0
            },
            {
                "maxAge": 1,
                "name": "Mr. Russell  Wallach",
                "age": 58,
                "title": "Global President of Sponsorship & Advertising Division",
                "yearBorn": 1966,
                "fiscalYear": 2024,
                "exercisedValue": 0,
                "unexercisedValue": 0
            },
            {
                "maxAge": 1,
                "name": "Mr. Arthur  Fogel",
                "age": 70,
                "title": "Chairman of Global Music Group & President of Global Touring Division",
                "yearBorn": 1954,
                "fiscalYear": 2024,
                "exercisedValue": 0,
                "unexercisedValue": 0
            }
        ],
        "auditRisk": 10,
        "boardRisk": 9,
        "compensationRisk": 9,
        "shareHolderRightsRisk": 9,
        "overallRisk": 9,
        "governanceEpochDate": 1759276800,
        "compensationAsOfEpochDate": 1735603200,
        "executiveTeam": [],
        "maxAge": 86400,
        "priceHint": 2,
        "previousClose": 149.95,
        "open": 149.5,
        "dayLow": 149.29,
        "dayHigh": 153.44,
        "regularMarketPreviousClose": 149.95,
        "regularMarketOpen": 149.5,
        "regularMarketDayLow": 149.29,
        "regularMarketDayHigh": 153.42,
        "payoutRatio": 0.0,
        "beta": 1.403,
        "trailingPE": 65.24894,
        "forwardPE": 63.361572,
        "volume": 3577587,
        "regularMarketVolume": 3577282,
        "averageVolume": 2310001,
        "averageVolume10days": 3201330,
        "averageDailyVolume10Day": 3201330,
        "bid": 152.78,
        "ask": 152.99,
        "bidSize": 2,
        "askSize": 1,
        "marketCap": 35566071808,
        "fiftyTwoWeekLow": 111.84,
        "fiftyTwoWeekHigh": 175.25,
        "allTimeHigh": 175.25,
        "allTimeLow": 2.47,
        "priceToSalesTrailing12Months": 1.5003487,
        "fiftyDayAverage": 161.3554,
        "twoHundredDayAverage": 144.1577,
        "trailingAnnualDividendRate": 0.0,
        "trailingAnnualDividendYield": 0.0,
        "currency": "USD",
        "tradeable": false,
        "enterpriseValue": 38089101312,
        "profitMargins": 0.03876,
        "floatShares": 155882070,
        "sharesOutstanding": 231950108,
        "sharesShort": 19255276,
        "sharesShortPriorMonth": 19826249,
        "sharesShortPreviousMonthDate": 1755216000,
        "dateShortInterest": 1757894400,
        "sharesPercentSharesOut": 0.083000004,
        "heldPercentInsiders": 0.32379,
        "heldPercentInstitutions": 0.81071,
        "shortRatio": 10.01,
        "shortPercentOfFloat": 0.1223,
        "impliedSharesOutstanding": 231950108,
        "bookValue": 1.565,
        "priceToBook": 97.97764,
        "lastFiscalYearEnd": 1735603200,
        "nextFiscalYearEnd": 1767139200,
        "mostRecentQuarter": 1751241600,
        "earningsQuarterlyGrowth": -0.183,
        "netIncomeToCommon": 547870016,
        "trailingEps": 2.35,
        "forwardEps": 2.42,
        "enterpriseToRevenue": 1.606,
        "enterpriseToEbitda": 18.949,
        "52WeekChange": 0.33064163,
        "SandP52WeekChange": 0.16845357,
        "quoteType": "EQUITY",
        "currentPrice": 153.44,
        "targetHighPrice": 195.0,
        "targetLowPrice": 130.0,
        "targetMeanPrice": 174.52632,
        "targetMedianPrice": 180.0,
        "recommendationMean": 1.65,
        "recommendationKey": "buy",
        "numberOfAnalystOpinions": 19,
        "totalCash": 7056974848,
        "totalCashPerShare": 30.425,
        "ebitda": 2010120960,
        "totalDebt": 8419643904,
        "quickRatio": 0.707,
        "currentRatio": 0.878,
        "totalRevenue": 23721437184,
        "debtToEquity": 365.185,
        "revenuePerShare": 102.671,
        "returnOnAssets": 0.04077,
        "returnOnEquity": 0.59354997,
        "grossProfits": 5987140096,
        "freeCashflow": 1802233600,
        "operatingCashflow": 1868942976,
        "earningsGrowth": -0.6,
        "revenueGrowth": 0.163,
        "grossMargins": 0.25239,
        "ebitdaMargins": 0.08474,
        "operatingMargins": 0.06933,
        "financialCurrency": "USD",
        "symbol": "LYV",
        "language": "en-US",
        "region": "US",
        "typeDisp": "Equity",
        "quoteSourceName": "Nasdaq Real Time Price",
        "triggerable": true,
        "customPriceAlertConfidence": "HIGH",
        "corporateActions": [],
        "regularMarketTime": 1760037436,
        "exchange": "NYQ",
        "messageBoardId": "finmb_384687",
        "exchangeTimezoneName": "America/New_York",
        "exchangeTimezoneShortName": "EDT",
        "gmtOffSetMilliseconds": -14400000,
        "market": "us_market",
        "esgPopulated": false,
        "regularMarketChangePercent": 2.2579527,
        "regularMarketPrice": 153.335,
        "shortName": "Live Nation Entertainment, Inc.",
        "longName": "Live Nation Entertainment, Inc.",
        "hasPrePostMarketData": true,
        "firstTradeDateMilliseconds": 1135175400000,
        "regularMarketChange": 3.3850098,
        "regularMarketDayRange": "149.29 - 153.42",
        "fullExchangeName": "NYSE",
        "averageDailyVolume3Month": 2310001,
        "fiftyTwoWeekLowChange": 41.49501,
        "fiftyTwoWeekLowChangePercent": 0.3710212,
        "fiftyTwoWeekRange": "111.84 - 175.25",
        "fiftyTwoWeekHighChange": -21.914993,
        "fiftyTwoWeekHighChangePercent": -0.12504989,
        "fiftyTwoWeekChangePercent": 33.064163,
        "earningsTimestamp": 1754596800,
        "earningsTimestampStart": 1762804800,
        "earningsTimestampEnd": 1762804800,
        "earningsCallTimestampStart": 1754600400,
        "earningsCallTimestampEnd": 1754600400,
        "isEarningsDateEstimate": true,
        "epsTrailingTwelveMonths": 2.35,
        "epsForward": 2.42,
        "epsCurrentYear": 1.47,
        "priceEpsCurrentYear": 104.309525,
        "fiftyDayAverageChange": -8.020386,
        "fiftyDayAverageChangePercent": -0.04970634,
        "twoHundredDayAverageChange": 9.177307,
        "twoHundredDayAverageChangePercent": 0.06366158,
        "sourceInterval": 15,
        "exchangeDataDelayedBy": 0,
        "averageAnalystRating": "1.6 - Buy",
        "cryptoTradeable": false,
        "marketState": "REGULAR",
        "displayName": "Live Nation Entertainment",
        "trailingPegRatio": 9.274
    },
    "income_statement": {
        "Tax Effect Of Unusual Items": {
            "2024-12-31": -19057080.0,
            "2023-12-31": 16038111.61601,
            "2022-12-31": 7582950.39998,
            "2021-12-31": 307611.091389,
            "2020-12-31": NaN
        },
        "Tax Rate For Calcs": {
            "2024-12-31": 0.21,
            "2023-12-31": 0.229368,
            "2022-12-31": 0.236362,
            "2021-12-31": 0.004059,
            "2020-12-31": NaN
        },
        "Normalized EBITDA": {
            "2024-12-31": 1706071000.0,
            "2023-12-31": 1710392000.0,
            "2022-12-31": 1186901000.0,
            "2021-12-31": 11661000.0,
            "2020-12-31": NaN
        },
        "Total Unusual Items": {
            "2024-12-31": -90748000.0,
            "2023-12-31": 69923000.0,
            "2022-12-31": 32082000.0,
            "2021-12-31": 75789000.0,
            "2020-12-31": NaN
        },
        "Total Unusual Items Excluding Goodwill": {
            "2024-12-31": -90748000.0,
            "2023-12-31": 69923000.0,
            "2022-12-31": 32082000.0,
            "2021-12-31": 75789000.0,
            "2020-12-31": NaN
        },
        "Net Income From Continuing Operation Net Minority Interest": {
            "2024-12-31": 896287000.0,
            "2023-12-31": 556893000.0,
            "2022-12-31": 266440000.0,
            "2021-12-31": -650904000.0,
            "2020-12-31": NaN
        },
        "Reconciled Depreciation": {
            "2024-12-31": 549923000.0,
            "2023-12-31": 516797000.0,
            "2022-12-31": 449976000.0,
            "2021-12-31": 416277000.0,
            "2020-12-31": NaN
        },
        "Reconciled Cost Of Revenue": {
            "2024-12-31": 17328154000.0,
            "2023-12-31": 17250530000.0,
            "2022-12-31": 12347611000.0,
            "2021-12-31": 4355989000.0,
            "2020-12-31": NaN
        },
        "EBITDA": {
            "2024-12-31": 1615323000.0,
            "2023-12-31": 1780315000.0,
            "2022-12-31": 1218983000.0,
            "2021-12-31": 87450000.0,
            "2020-12-31": NaN
        },
        "EBIT": {
            "2024-12-31": 1065400000.0,
            "2023-12-31": 1263518000.0,
            "2022-12-31": 769007000.0,
            "2021-12-31": -328827000.0,
            "2020-12-31": NaN
        },
        "Net Interest Income": {
            "2024-12-31": -169720000.0,
            "2023-12-31": -112426000.0,
            "2022-12-31": -200863000.0,
            "2021-12-31": -275815000.0,
            "2020-12-31": NaN
        },
        "Interest Expense": {
            "2024-12-31": 325974000.0,
            "2023-12-31": 350244000.0,
            "2022-12-31": 278483000.0,
            "2021-12-31": 282440000.0,
            "2020-12-31": NaN
        },
        "Interest Income": {
            "2024-12-31": 156254000.0,
            "2023-12-31": 237818000.0,
            "2022-12-31": 77620000.0,
            "2021-12-31": 6625000.0,
            "2020-12-31": NaN
        },
        "Normalized Income": {
            "2024-12-31": 967977920.0,
            "2023-12-31": 503008111.61601,
            "2022-12-31": 241940950.39998,
            "2021-12-31": -726385388.908611,
            "2020-12-31": NaN
        },
        "Net Income From Continuing And Discontinued Operation": {
            "2024-12-31": 896287000.0,
            "2023-12-31": 556893000.0,
            "2022-12-31": 266440000.0,
            "2021-12-31": -650904000.0,
            "2020-12-31": NaN
        },
        "Total Expenses": {
            "2024-12-31": 22342130000.0,
            "2023-12-31": 21655311000.0,
            "2022-12-31": 15991305000.0,
            "2021-12-31": 6678516000.0,
            "2020-12-31": NaN
        },
        "Total Operating Income As Reported": {
            "2024-12-31": 824510000.0,
            "2023-12-31": 1084933000.0,
            "2022-12-31": 722031000.0,
            "2021-12-31": -417858000.0,
            "2020-12-31": NaN
        },
        "Diluted Average Shares": {
            "2024-12-31": 236352449.0,
            "2023-12-31": 230977326.0,
            "2022-12-31": 231556866.0,
            "2021-12-31": 217190862.0,
            "2020-12-31": NaN
        },
        "Basic Average Shares": {
            "2024-12-31": 230124255.0,
            "2023-12-31": 228628390.0,
            "2022-12-31": 224809558.0,
            "2021-12-31": 217190862.0,
            "2020-12-31": NaN
        },
        "Diluted EPS": {
            "2024-12-31": 2.74,
            "2023-12-31": 1.34,
            "2022-12-31": 0.64,
            "2021-12-31": -3.09,
            "2020-12-31": NaN
        },
        "Basic EPS": {
            "2024-12-31": 2.77,
            "2023-12-31": 1.35,
            "2022-12-31": 0.66,
            "2021-12-31": -3.09,
            "2020-12-31": NaN
        },
        "Diluted NI Availto Com Stockholders": {
            "2024-12-31": 647398000.0,
            "2023-12-31": 309455000.0,
            "2022-12-31": 119670000.0,
            "2021-12-31": -670675000.0,
            "2020-12-31": NaN
        },
        "Average Dilution Earnings": {
            "2024-12-31": 9187000.0,
            "2023-12-31": 0.0,
            "2022-12-31": 0.0,
            "2021-12-31": NaN,
            "2020-12-31": NaN
        },
        "Net Income Common Stockholders": {
            "2024-12-31": 638211000.0,
            "2023-12-31": 309455000.0,
            "2022-12-31": 119670000.0,
            "2021-12-31": -670675000.0,
            "2020-12-31": NaN
        },
        "Otherunder Preferred Stock Dividend": {
            "2024-12-31": 258076000.0,
            "2023-12-31": 247438000.0,
            "2022-12-31": 146770000.0,
            "2021-12-31": 19771000.0,
            "2020-12-31": NaN
        },
        "Net Income": {
            "2024-12-31": 896287000.0,
            "2023-12-31": 556893000.0,
            "2022-12-31": 266440000.0,
            "2021-12-31": -650904000.0,
            "2020-12-31": NaN
        },
        "Minority Interests": {
            "2024-12-31": -234837000.0,
            "2023-12-31": -146905000.0,
            "2022-12-31": -108143000.0,
            "2021-12-31": -42118000.0,
            "2020-12-31": NaN
        },
        "Net Income Including Noncontrolling Interests": {
            "2024-12-31": 1131124000.0,
            "2023-12-31": 703798000.0,
            "2022-12-31": 374583000.0,
            "2021-12-31": -608786000.0,
            "2020-12-31": NaN
        },
        "Net Income Continuous Operations": {
            "2024-12-31": 1131124000.0,
            "2023-12-31": 703798000.0,
            "2022-12-31": 374583000.0,
            "2021-12-31": -608786000.0,
            "2020-12-31": NaN
        },
        "Tax Provision": {
            "2024-12-31": -391698000.0,
            "2023-12-31": 209476000.0,
            "2022-12-31": 115941000.0,
            "2021-12-31": -2481000.0,
            "2020-12-31": NaN
        },
        "Pretax Income": {
            "2024-12-31": 739426000.0,
            "2023-12-31": 913274000.0,
            "2022-12-31": 490524000.0,
            "2021-12-31": -611267000.0,
            "2020-12-31": NaN
        },
        "Other Income Expense": {
            "2024-12-31": 95651000.0,
            "2023-12-31": -45306000.0,
            "2022-12-31": 1438000.0,
            "2021-12-31": 74617000.0,
            "2020-12-31": NaN
        },
        "Other Non Operating Income Expenses": {
            "2024-12-31": 203074000.0,
            "2023-12-31": -109774000.0,
            "2022-12-31": -41215000.0,
            "2021-12-31": -3692000.0,
            "2020-12-31": NaN
        },
        "Special Income Charges": {
            "2024-12-31": 8452000.0,
            "2023-12-31": -4577000.0,
            "2022-12-31": 32082000.0,
            "2021-12-31": 75789000.0,
            "2020-12-31": NaN
        },
        "Gain On Sale Of Ppe": {
            "2024-12-31": 11015000.0,
            "2023-12-31": 13927000.0,
            "2022-12-31": 32082000.0,
            "2021-12-31": 1211000.0,
            "2020-12-31": NaN
        },
        "Gain On Sale Of Business": {
            "2024-12-31": NaN,
            "2023-12-31": -341000.0,
            "2022-12-31": 448000.0,
            "2021-12-31": 83578000.0,
            "2020-12-31": -1727000.0
        },
        "Other Special Charges": {
            "2024-12-31": 2563000.0,
            "2023-12-31": 18504000.0,
            "2022-12-31": NaN,
            "2021-12-31": NaN,
            "2020-12-31": NaN
        },
        "Restructuring And Mergern Acquisition": {
            "2024-12-31": NaN,
            "2023-12-31": 300000.0,
            "2022-12-31": 1000000.0,
            "2021-12-31": 9000000.0,
            "2020-12-31": NaN
        },
        "Earnings From Equity Interest": {
            "2024-12-31": -16675000.0,
            "2023-12-31": -5455000.0,
            "2022-12-31": 10571000.0,
            "2021-12-31": 2520000.0,
            "2020-12-31": NaN
        },
        "Gain On Sale Of Security": {
            "2024-12-31": -99200000.0,
            "2023-12-31": 74500000.0,
            "2022-12-31": NaN,
            "2021-12-31": NaN,
            "2020-12-31": NaN
        },
        "Net Non Operating Interest Income Expense": {
            "2024-12-31": -169720000.0,
            "2023-12-31": -112426000.0,
            "2022-12-31": -200863000.0,
            "2021-12-31": -275815000.0,
            "2020-12-31": NaN
        },
        "Interest Expense Non Operating": {
            "2024-12-31": 325974000.0,
            "2023-12-31": 350244000.0,
            "2022-12-31": 278483000.0,
            "2021-12-31": 282440000.0,
            "2020-12-31": NaN
        },
        "Interest Income Non Operating": {
            "2024-12-31": 156254000.0,
            "2023-12-31": 237818000.0,
            "2022-12-31": 77620000.0,
            "2021-12-31": 6625000.0,
            "2020-12-31": NaN
        },
        "Operating Income": {
            "2024-12-31": 813495000.0,
            "2023-12-31": 1071006000.0,
            "2022-12-31": 689949000.0,
            "2021-12-31": -410069000.0,
            "2020-12-31": NaN
        },
        "Operating Expense": {
            "2024-12-31": 5013976000.0,
            "2023-12-31": 4404781000.0,
            "2022-12-31": 3643694000.0,
            "2021-12-31": 2322527000.0,
            "2020-12-31": NaN
        },
        "Other Operating Expenses": {
            "2024-12-31": 367629000.0,
            "2023-12-31": 330817000.0,
            "2022-12-31": 237834000.0,
            "2021-12-31": 160428000.0,
            "2020-12-31": NaN
        },
        "Depreciation Amortization Depletion Income Statement": {
            "2024-12-31": 549923000.0,
            "2023-12-31": 516797000.0,
            "2022-12-31": 449976000.0,
            "2021-12-31": 416277000.0,
            "2020-12-31": NaN
        },
        "Depreciation And Amortization In Income Statement": {
            "2024-12-31": 549923000.0,
            "2023-12-31": 516797000.0,
            "2022-12-31": 449976000.0,
            "2021-12-31": 416277000.0,
            "2020-12-31": NaN
        },
        "Selling General And Administration": {
            "2024-12-31": 4096424000.0,
            "2023-12-31": 3557167000.0,
            "2022-12-31": 2955884000.0,
            "2021-12-31": 1745822000.0,
            "2020-12-31": NaN
        },
        "Selling And Marketing Expense": {
            "2024-12-31": 54600000.0,
            "2023-12-31": 47700000.0,
            "2022-12-31": 32000000.0,
            "2021-12-31": 18100000.0,
            "2020-12-31": NaN
        },
        "General And Administrative Expense": {
            "2024-12-31": 4041824000.0,
            "2023-12-31": 3509467000.0,
            "2022-12-31": 2923884000.0,
            "2021-12-31": 1727722000.0,
            "2020-12-31": NaN
        },
        "Other Gand A": {
            "2024-12-31": 4041824000.0,
            "2023-12-31": 3509467000.0,
            "2022-12-31": 2923884000.0,
            "2021-12-31": 1727722000.0,
            "2020-12-31": NaN
        },
        "Gross Profit": {
            "2024-12-31": 5827471000.0,
            "2023-12-31": 5475787000.0,
            "2022-12-31": 4333643000.0,
            "2021-12-31": 1912458000.0,
            "2020-12-31": NaN
        },
        "Cost Of Revenue": {
            "2024-12-31": 17328154000.0,
            "2023-12-31": 17250530000.0,
            "2022-12-31": 12347611000.0,
            "2021-12-31": 4355989000.0,
            "2020-12-31": NaN
        },
        "Total Revenue": {
            "2024-12-31": 23155625000.0,
            "2023-12-31": 22726317000.0,
            "2022-12-31": 16681254000.0,
            "2021-12-31": 6268447000.0,
            "2020-12-31": NaN
        },
        "Operating Revenue": {
            "2024-12-31": 23155625000.0,
            "2023-12-31": 22726317000.0,
            "2022-12-31": 16681254000.0,
            "2021-12-31": 6268447000.0,
            "2020-12-31": NaN
        }
    },
    "balance_sheet": {
        "Treasury Shares Number": {
            "2024-12-31": 408024.0,
            "2023-12-31": 408024.0,
            "2022-12-31": 408024.0,
            "2021-12-31": 408024.0,
            "2020-12-31": NaN
        },
        "Ordinary Shares Number": {
            "2024-12-31": 234363735.0,
            "2023-12-31": 233303152.0,
            "2022-12-31": 231263623.0,
            "2021-12-31": 224674579.0,
            "2020-12-31": NaN
        },
        "Share Issued": {
            "2024-12-31": 234771759.0,
            "2023-12-31": 233711176.0,
            "2022-12-31": 231671647.0,
            "2021-12-31": 225082603.0,
            "2020-12-31": NaN
        },
        "Net Debt": {
            "2024-12-31": 342645000.0,
            "2023-12-31": 361546000.0,
            "2022-12-31": 297042000.0,
            "2021-12-31": 846009000.0,
            "2020-12-31": NaN
        },
        "Total Debt": {
            "2024-12-31": 8271741000.0,
            "2023-12-31": 8437924000.0,
            "2022-12-31": 7698256000.0,
            "2021-12-31": 7460517000.0,
            "2020-12-31": NaN
        },
        "Tangible Book Value": {
            "2024-12-31": -3814018000.0,
            "2023-12-31": -4282741000.0,
            "2022-12-31": -4316283000.0,
            "2021-12-31": -4568886000.0,
            "2020-12-31": NaN
        },
        "Invested Capital": {
            "2024-12-31": 6611332000.0,
            "2023-12-31": 6541107000.0,
            "2022-12-31": 5535930000.0,
            "2021-12-31": 5148087000.0,
            "2020-12-31": NaN
        },
        "Working Capital": {
            "2024-12-31": -68142000.0,
            "2023-12-31": -451085000.0,
            "2022-12-31": -143793000.0,
            "2021-12-31": -171629000.0,
            "2020-12-31": NaN
        },
        "Net Tangible Assets": {
            "2024-12-31": -3814018000.0,
            "2023-12-31": -4282741000.0,
            "2022-12-31": -4316283000.0,
            "2021-12-31": -4568886000.0,
            "2020-12-31": NaN
        },
        "Capital Lease Obligations": {
            "2024-12-31": 1833672000.0,
            "2023-12-31": 1844512000.0,
            "2022-12-31": 1794757000.0,
            "2021-12-31": 1729779000.0,
            "2020-12-31": NaN
        },
        "Common Stock Equity": {
            "2024-12-31": 173263000.0,
            "2023-12-31": -52305000.0,
            "2022-12-31": -367569000.0,
            "2021-12-31": -582651000.0,
            "2020-12-31": NaN
        },
        "Total Capitalization": {
            "2024-12-31": 6350431000.0,
            "2023-12-31": 5406721000.0,
            "2022-12-31": 4915898000.0,
            "2021-12-31": 4562833000.0,
            "2020-12-31": NaN
        },
        "Total Equity Gross Minority Interest": {
            "2024-12-31": 1945295000.0,
            "2023-12-31": 1411930000.0,
            "2022-12-31": 763563000.0,
            "2021-12-31": 363467000.0,
            "2020-12-31": NaN
        },
        "Minority Interest": {
            "2024-12-31": 1772032000.0,
            "2023-12-31": 1464235000.0,
            "2022-12-31": 1131132000.0,
            "2021-12-31": 946118000.0,
            "2020-12-31": NaN
        },
        "Stockholders Equity": {
            "2024-12-31": 173263000.0,
            "2023-12-31": -52305000.0,
            "2022-12-31": -367569000.0,
            "2021-12-31": -582651000.0,
            "2020-12-31": NaN
        },
        "Gains Losses Not Affecting Retained Earnings": {
            "2024-12-31": -335112000.0,
            "2023-12-31": 27450000.0,
            "2022-12-31": -90076000.0,
            "2021-12-31": -147964000.0,
            "2020-12-31": NaN
        },
        "Other Equity Adjustments": {
            "2024-12-31": -335112000.0,
            "2023-12-31": 27450000.0,
            "2022-12-31": -90076000.0,
            "2021-12-31": -147964000.0,
            "2020-12-31": NaN
        },
        "Treasury Stock": {
            "2024-12-31": 6865000.0,
            "2023-12-31": 6865000.0,
            "2022-12-31": 6865000.0,
            "2021-12-31": 6865000.0,
            "2020-12-31": NaN
        },
        "Retained Earnings": {
            "2024-12-31": -1546819000.0,
            "2023-12-31": -2443106000.0,
            "2022-12-31": -2971229000.0,
            "2021-12-31": -3327737000.0,
            "2020-12-31": NaN
        },
        "Additional Paid In Capital": {
            "2024-12-31": 2059746000.0,
            "2023-12-31": 2367918000.0,
            "2022-12-31": 2698316000.0,
            "2021-12-31": 2897695000.0,
            "2020-12-31": NaN
        },
        "Capital Stock": {
            "2024-12-31": 2313000.0,
            "2023-12-31": 2298000.0,
            "2022-12-31": 2285000.0,
            "2021-12-31": 2220000.0,
            "2020-12-31": NaN
        },
        "Common Stock": {
            "2024-12-31": 2313000.0,
            "2023-12-31": 2298000.0,
            "2022-12-31": 2285000.0,
            "2021-12-31": 2220000.0,
            "2020-12-31": NaN
        },
        "Preferred Stock": {
            "2024-12-31": 0.0,
            "2023-12-31": 0.0,
            "2022-12-31": 0.0,
            "2021-12-31": 0.0,
            "2020-12-31": NaN
        },
        "Total Liabilities Net Minority Interest": {
            "2024-12-31": 17693476000.0,
            "2023-12-31": 17617710000.0,
            "2022-12-31": 15697278000.0,
            "2021-12-31": 14038851000.0,
            "2020-12-31": NaN
        },
        "Total Non Current Liabilities Net Minority Interest": {
            "2024-12-31": 8335197000.0,
            "2023-12-31": 7633276000.0,
            "2022-12-31": 7393963000.0,
            "2021-12-31": 7183129000.0,
            "2020-12-31": NaN
        },
        "Other Non Current Liabilities": {
            "2024-12-31": 196813000.0,
            "2023-12-31": 73745000.0,
            "2022-12-31": 37513000.0,
            "2021-12-31": 65094000.0,
            "2020-12-31": NaN
        },
        "Preferred Securities Outside Stock Equity": {
            "2024-12-31": NaN,
            "2023-12-31": NaN,
            "2022-12-31": NaN,
            "2021-12-31": 551921000.0,
            "2020-12-31": 272449000.0
        },
        "Non Current Deferred Liabilities": {
            "2024-12-31": 280950000.0,
            "2023-12-31": 414414000.0,
            "2022-12-31": 418458000.0,
            "2021-12-31": 366487000.0,
            "2020-12-31": NaN
        },
        "Non Current Deferred Revenue": {
            "2024-12-31": 120064000.0,
            "2023-12-31": 60555000.0,
            "2022-12-31": 56953000.0,
            "2021-12-31": 116682000.0,
            "2020-12-31": NaN
        },
        "Non Current Deferred Taxes Liabilities": {
            "2024-12-31": 140151000.0,
            "2023-12-31": 324698000.0,
            "2022-12-31": 305524000.0,
            "2021-12-31": 236549000.0,
            "2020-12-31": NaN
        },
        "Long Term Debt And Capital Lease Obligation": {
            "2024-12-31": 7857434000.0,
            "2023-12-31": 7145117000.0,
            "2022-12-31": 6937992000.0,
            "2021-12-31": 6751548000.0,
            "2020-12-31": NaN
        },
        "Long Term Capital Lease Obligation": {
            "2024-12-31": 1680266000.0,
            "2023-12-31": 1686091000.0,
            "2022-12-31": 1654525000.0,
            "2021-12-31": 1606064000.0,
            "2020-12-31": NaN
        },
        "Long Term Debt": {
            "2024-12-31": 6177168000.0,
            "2023-12-31": 5459026000.0,
            "2022-12-31": 5283467000.0,
            "2021-12-31": 5145484000.0,
            "2020-12-31": NaN
        },
        "Current Liabilities": {
            "2024-12-31": 9358279000.0,
            "2023-12-31": 9984434000.0,
            "2022-12-31": 8303315000.0,
            "2021-12-31": 6855722000.0,
            "2020-12-31": NaN
        },
        "Other Current Liabilities": {
            "2024-12-31": 22089000.0,
            "2023-12-31": 29595000.0,
            "2022-12-31": 40867000.0,
            "2021-12-31": 33260000.0,
            "2020-12-31": NaN
        },
        "Current Deferred Liabilities": {
            "2024-12-31": 3761893000.0,
            "2023-12-31": 3496863000.0,
            "2022-12-31": 3162649000.0,
            "2021-12-31": 2824619000.0,
            "2020-12-31": NaN
        },
        "Current Deferred Revenue": {
            "2024-12-31": 3721092000.0,
            "2023-12-31": 3398028000.0,
            "2022-12-31": 3134800000.0,
            "2021-12-31": 2774792000.0,
            "2020-12-31": NaN
        },
        "Current Debt And Capital Lease Obligation": {
            "2024-12-31": 414307000.0,
            "2023-12-31": 1292807000.0,
            "2022-12-31": 760264000.0,
            "2021-12-31": 708969000.0,
            "2020-12-31": NaN
        },
        "Current Capital Lease Obligation": {
            "2024-12-31": 153406000.0,
            "2023-12-31": 158421000.0,
            "2022-12-31": 140232000.0,
            "2021-12-31": 123715000.0,
            "2020-12-31": NaN
        },
        "Current Debt": {
            "2024-12-31": 260901000.0,
            "2023-12-31": 1134386000.0,
            "2022-12-31": 620032000.0,
            "2021-12-31": 585254000.0,
            "2020-12-31": NaN
        },
        "Other Current Borrowings": {
            "2024-12-31": 260901000.0,
            "2023-12-31": 1134386000.0,
            "2022-12-31": 620032000.0,
            "2021-12-31": 585254000.0,
            "2020-12-31": NaN
        },
        "Pensionand Other Post Retirement Benefit Plans Current": {
            "2024-12-31": 512531000.0,
            "2023-12-31": 529987000.0,
            "2022-12-31": 540018000.0,
            "2021-12-31": 287079000.0,
            "2020-12-31": NaN
        },
        "Payables And Accrued Expenses": {
            "2024-12-31": 4647459000.0,
            "2023-12-31": 4635182000.0,
            "2022-12-31": 3799517000.0,
            "2021-12-31": 3001795000.0,
            "2020-12-31": NaN
        },
        "Current Accrued Expenses": {
            "2024-12-31": 2544803000.0,
            "2023-12-31": 2500825000.0,
            "2022-12-31": 1828416000.0,
            "2021-12-31": 1358827000.0,
            "2020-12-31": NaN
        },
        "Payables": {
            "2024-12-31": 2102656000.0,
            "2023-12-31": 2134357000.0,
            "2022-12-31": 1971101000.0,
            "2021-12-31": 1642968000.0,
            "2020-12-31": NaN
        },
        "Accounts Payable": {
            "2024-12-31": 2102656000.0,
            "2023-12-31": 2134357000.0,
            "2022-12-31": 1971101000.0,
            "2021-12-31": 1642968000.0,
            "2020-12-31": NaN
        },
        "Total Assets": {
            "2024-12-31": 19638771000.0,
            "2023-12-31": 19029640000.0,
            "2022-12-31": 16460841000.0,
            "2021-12-31": 14402318000.0,
            "2020-12-31": NaN
        },
        "Total Non Current Assets": {
            "2024-12-31": 10348634000.0,
            "2023-12-31": 9496291000.0,
            "2022-12-31": 8301319000.0,
            "2021-12-31": 7718225000.0,
            "2020-12-31": NaN
        },
        "Other Non Current Assets": {
            "2024-12-31": 472819000.0,
            "2023-12-31": 268382000.0,
            "2022-12-31": 223570000.0,
            "2021-12-31": 185437000.0,
            "2020-12-31": NaN
        },
        "Non Current Prepaid Assets": {
            "2024-12-31": 520482000.0,
            "2023-12-31": 623154000.0,
            "2022-12-31": 568558000.0,
            "2021-12-31": 552697000.0,
            "2020-12-31": NaN
        },
        "Non Current Deferred Assets": {
            "2024-12-31": 577932000.0,
            "2023-12-31": 42840000.0,
            "2022-12-31": NaN,
            "2021-12-31": NaN,
            "2020-12-31": NaN
        },
        "Non Current Deferred Taxes Assets": {
            "2024-12-31": 577932000.0,
            "2023-12-31": 42840000.0,
            "2022-12-31": NaN,
            "2021-12-31": NaN,
            "2020-12-31": NaN
        },
        "Non Current Note Receivables": {
            "2024-12-31": 226021000.0,
            "2023-12-31": 176133000.0,
            "2022-12-31": 92630000.0,
            "2021-12-31": 69371000.0,
            "2020-12-31": NaN
        },
        "Investments And Advances": {
            "2024-12-31": 504194000.0,
            "2023-12-31": 447494000.0,
            "2022-12-31": 408789000.0,
            "2021-12-31": 293645000.0,
            "2020-12-31": NaN
        },
        "Long Term Equity Investment": {
            "2024-12-31": 504194000.0,
            "2023-12-31": 447494000.0,
            "2022-12-31": 408789000.0,
            "2021-12-31": 293645000.0,
            "2020-12-31": NaN
        },
        "Goodwill And Other Intangible Assets": {
            "2024-12-31": 3987281000.0,
            "2023-12-31": 4230436000.0,
            "2022-12-31": 3948714000.0,
            "2021-12-31": 3986235000.0,
            "2020-12-31": NaN
        },
        "Other Intangible Assets": {
            "2024-12-31": 1366370000.0,
            "2023-12-31": 1538970000.0,
            "2022-12-31": 1419334000.0,
            "2021-12-31": 1395366000.0,
            "2020-12-31": NaN
        },
        "Goodwill": {
            "2024-12-31": 2620911000.0,
            "2023-12-31": 2691466000.0,
            "2022-12-31": 2529380000.0,
            "2021-12-31": 2590869000.0,
            "2020-12-31": NaN
        },
        "Net PPE": {
            "2024-12-31": 4059905000.0,
            "2023-12-31": 3707852000.0,
            "2022-12-31": 3059058000.0,
            "2021-12-31": 2630840000.0,
            "2020-12-31": NaN
        },
        "Accumulated Depreciation": {
            "2024-12-31": -1896034000.0,
            "2023-12-31": -1794191000.0,
            "2022-12-31": -1851955000.0,
            "2021-12-31": -1728198000.0,
            "2020-12-31": NaN
        },
        "Gross PPE": {
            "2024-12-31": 5955939000.0,
            "2023-12-31": 5502043000.0,
            "2022-12-31": 4911013000.0,
            "2021-12-31": 4359038000.0,
            "2020-12-31": NaN
        },
        "Construction In Progress": {
            "2024-12-31": 386880000.0,
            "2023-12-31": 317028000.0,
            "2022-12-31": 244618000.0,
            "2021-12-31": 173865000.0,
            "2020-12-31": NaN
        },
        "Other Properties": {
            "2024-12-31": 1618033000.0,
            "2023-12-31": 1606389000.0,
            "2022-12-31": 1571395000.0,
            "2021-12-31": 1538911000.0,
            "2020-12-31": NaN
        },
        "Machinery Furniture Equipment": {
            "2024-12-31": 1625097000.0,
            "2023-12-31": 1535031000.0,
            "2022-12-31": 1446512000.0,
            "2021-12-31": 1321984000.0,
            "2020-12-31": NaN
        },
        "Properties": {
            "2024-12-31": 2325929000.0,
            "2023-12-31": 2043595000.0,
            "2022-12-31": 1648488000.0,
            "2021-12-31": 1324278000.0,
            "2020-12-31": NaN
        },
        "Current Assets": {
            "2024-12-31": 9290137000.0,
            "2023-12-31": 9533349000.0,
            "2022-12-31": 8159522000.0,
            "2021-12-31": 6684093000.0,
            "2020-12-31": NaN
        },
        "Other Current Assets": {
            "2024-12-31": 107365000.0,
            "2023-12-31": 33176000.0,
            "2022-12-31": 58986000.0,
            "2021-12-31": 21802000.0,
            "2020-12-31": NaN
        },
        "Restricted Cash": {
            "2024-12-31": 10685000.0,
            "2023-12-31": 7090000.0,
            "2022-12-31": 5917000.0,
            "2021-12-31": 3063000.0,
            "2020-12-31": NaN
        },
        "Prepaid Assets": {
            "2024-12-31": 1247184000.0,
            "2023-12-31": 1147581000.0,
            "2022-12-31": 949826000.0,
            "2021-12-31": 654894000.0,
            "2020-12-31": NaN
        },
        "Inventory": {
            "2024-12-31": 50145000.0,
            "2023-12-31": 45141000.0,
            "2022-12-31": 38725000.0,
            "2021-12-31": 33826000.0,
            "2020-12-31": NaN
        },
        "Receivables": {
            "2024-12-31": 1779334000.0,
            "2023-12-31": 2068495000.0,
            "2022-12-31": 1499611000.0,
            "2021-12-31": 1085779000.0,
            "2020-12-31": NaN
        },
        "Notes Receivable": {
            "2024-12-31": 32018000.0,
            "2023-12-31": 43846000.0,
            "2022-12-31": 34228000.0,
            "2021-12-31": 19206000.0,
            "2020-12-31": NaN
        },
        "Accounts Receivable": {
            "2024-12-31": 1747316000.0,
            "2023-12-31": 2024649000.0,
            "2022-12-31": 1465383000.0,
            "2021-12-31": 1066573000.0,
            "2020-12-31": NaN
        },
        "Allowance For Doubtful Accounts Receivable": {
            "2024-12-31": -72663000.0,
            "2023-12-31": -82350000.0,
            "2022-12-31": -63294000.0,
            "2021-12-31": -50491000.0,
            "2020-12-31": NaN
        },
        "Gross Accounts Receivable": {
            "2024-12-31": 1819979000.0,
            "2023-12-31": 2106999000.0,
            "2022-12-31": 1528677000.0,
            "2021-12-31": 1117064000.0,
            "2020-12-31": NaN
        },
        "Cash Cash Equivalents And Short Term Investments": {
            "2024-12-31": 6095424000.0,
            "2023-12-31": 6231866000.0,
            "2022-12-31": 5606457000.0,
            "2021-12-31": 4884729000.0,
            "2020-12-31": NaN
        },
        "Cash And Cash Equivalents": {
            "2024-12-31": 6095424000.0,
            "2023-12-31": 6231866000.0,
            "2022-12-31": 5606457000.0,
            "2021-12-31": 4884729000.0,
            "2020-12-31": NaN
        }
    },
    "cash_flow": {
        "Free Cash Flow": {
            "2024-12-31": 1050019000.0,
            "2023-12-31": 887717000.0,
            "2022-12-31": 1481761000.0,
            "2021-12-31": 1620734000.0,
            "2020-12-31": NaN
        },
        "Repayment Of Debt": {
            "2024-12-31": -1959725000.0,
            "2023-12-31": -730643000.0,
            "2022-12-31": -45792000.0,
            "2021-12-31": -109705000.0,
            "2020-12-31": NaN
        },
        "Issuance Of Debt": {
            "2024-12-31": 1671842000.0,
            "2023-12-31": 1061026000.0,
            "2022-12-31": 122251000.0,
            "2021-12-31": 903827000.0,
            "2020-12-31": NaN
        },
        "Issuance Of Capital Stock": {
            "2024-12-31": NaN,
            "2023-12-31": 0.0,
            "2022-12-31": 0.0,
            "2021-12-31": 449630000.0,
            "2020-12-31": 0.0
        },
        "Capital Expenditure": {
            "2024-12-31": -675156000.0,
            "2023-12-31": -475257000.0,
            "2022-12-31": -353286000.0,
            "2021-12-31": -159834000.0,
            "2020-12-31": NaN
        },
        "Interest Paid Supplemental Data": {
            "2024-12-31": 131234000.0,
            "2023-12-31": 57367000.0,
            "2022-12-31": 180878000.0,
            "2021-12-31": 224402000.0,
            "2020-12-31": NaN
        },
        "Income Tax Paid Supplemental Data": {
            "2024-12-31": 253652000.0,
            "2023-12-31": 175148000.0,
            "2022-12-31": 43859000.0,
            "2021-12-31": 15911000.0,
            "2020-12-31": NaN
        },
        "End Cash Position": {
            "2024-12-31": 6106109000.0,
            "2023-12-31": 6238956000.0,
            "2022-12-31": 5620194000.0,
            "2021-12-31": 4887792000.0,
            "2020-12-31": NaN
        },
        "Beginning Cash Position": {
            "2024-12-31": 6238956000.0,
            "2023-12-31": 5620194000.0,
            "2022-12-31": 4887792000.0,
            "2021-12-31": 2546439000.0,
            "2020-12-31": NaN
        },
        "Effect Of Exchange Rate Changes": {
            "2024-12-31": -345191000.0,
            "2023-12-31": 38874000.0,
            "2022-12-31": -174614000.0,
            "2021-12-31": -43585000.0,
            "2020-12-31": NaN
        },
        "Changes In Cash": {
            "2024-12-31": 212344000.0,
            "2023-12-31": 579888000.0,
            "2022-12-31": 907016000.0,
            "2021-12-31": 2384938000.0,
            "2020-12-31": NaN
        },
        "Financing Cash Flow": {
            "2024-12-31": -658550000.0,
            "2023-12-31": -87281000.0,
            "2022-12-31": -143340000.0,
            "2021-12-31": 1171332000.0,
            "2020-12-31": NaN
        },
        "Cash Flow From Continuing Financing Activities": {
            "2024-12-31": -658550000.0,
            "2023-12-31": -87281000.0,
            "2022-12-31": -143340000.0,
            "2021-12-31": 1171332000.0,
            "2020-12-31": NaN
        },
        "Net Other Financing Charges": {
            "2024-12-31": -396719000.0,
            "2023-12-31": -436928000.0,
            "2022-12-31": -255574000.0,
            "2021-12-31": -103038000.0,
            "2020-12-31": NaN
        },
        "Proceeds From Stock Option Exercised": {
            "2024-12-31": 26052000.0,
            "2023-12-31": 19264000.0,
            "2022-12-31": 35775000.0,
            "2021-12-31": 30618000.0,
            "2020-12-31": NaN
        },
        "Net Common Stock Issuance": {
            "2024-12-31": NaN,
            "2023-12-31": 0.0,
            "2022-12-31": 0.0,
            "2021-12-31": 449630000.0,
            "2020-12-31": 0.0
        },
        "Common Stock Issuance": {
            "2024-12-31": NaN,
            "2023-12-31": 0.0,
            "2022-12-31": 0.0,
            "2021-12-31": 449630000.0,
            "2020-12-31": 0.0
        },
        "Net Issuance Payments Of Debt": {
            "2024-12-31": -287883000.0,
            "2023-12-31": 330383000.0,
            "2022-12-31": 76459000.0,
            "2021-12-31": 794122000.0,
            "2020-12-31": NaN
        },
        "Net Long Term Debt Issuance": {
            "2024-12-31": -287883000.0,
            "2023-12-31": 330383000.0,
            "2022-12-31": 76459000.0,
            "2021-12-31": 794122000.0,
            "2020-12-31": NaN
        },
        "Long Term Debt Payments": {
            "2024-12-31": -1959725000.0,
            "2023-12-31": -730643000.0,
            "2022-12-31": -45792000.0,
            "2021-12-31": -109705000.0,
            "2020-12-31": NaN
        },
        "Long Term Debt Issuance": {
            "2024-12-31": 1671842000.0,
            "2023-12-31": 1061026000.0,
            "2022-12-31": 122251000.0,
            "2021-12-31": 903827000.0,
            "2020-12-31": NaN
        },
        "Investing Cash Flow": {
            "2024-12-31": -854281000.0,
            "2023-12-31": -695805000.0,
            "2022-12-31": -784691000.0,
            "2021-12-31": -566962000.0,
            "2020-12-31": NaN
        },
        "Cash Flow From Continuing Investing Activities": {
            "2024-12-31": -854281000.0,
            "2023-12-31": -695805000.0,
            "2022-12-31": -784691000.0,
            "2021-12-31": -566962000.0,
            "2020-12-31": NaN
        },
        "Net Other Investing Changes": {
            "2024-12-31": -54729000.0,
            "2023-12-31": -149616000.0,
            "2022-12-31": -86891000.0,
            "2021-12-31": -2720000.0,
            "2020-12-31": NaN
        },
        "Net Business Purchase And Sale": {
            "2024-12-31": -124396000.0,
            "2023-12-31": -70932000.0,
            "2022-12-31": -344514000.0,
            "2021-12-31": -404408000.0,
            "2020-12-31": NaN
        },
        "Sale Of Business": {
            "2024-12-31": 19594000.0,
            "2023-12-31": 1524000.0,
            "2022-12-31": 3863000.0,
            "2021-12-31": 90432000.0,
            "2020-12-31": NaN
        },
        "Purchase Of Business": {
            "2024-12-31": -143990000.0,
            "2023-12-31": -72456000.0,
            "2022-12-31": -348377000.0,
            "2021-12-31": -494840000.0,
            "2020-12-31": NaN
        },
        "Net Intangibles Purchase And Sale": {
            "2024-12-31": -8522000.0,
            "2023-12-31": -36653000.0,
            "2022-12-31": -6080000.0,
            "2021-12-31": -7100000.0,
            "2020-12-31": NaN
        },
        "Purchase Of Intangibles": {
            "2024-12-31": -8522000.0,
            "2023-12-31": -36653000.0,
            "2022-12-31": -6080000.0,
            "2021-12-31": -7100000.0,
            "2020-12-31": NaN
        },
        "Net PPE Purchase And Sale": {
            "2024-12-31": -666634000.0,
            "2023-12-31": -438604000.0,
            "2022-12-31": -347206000.0,
            "2021-12-31": -152734000.0,
            "2020-12-31": NaN
        },
        "Purchase Of PPE": {
            "2024-12-31": -666634000.0,
            "2023-12-31": -438604000.0,
            "2022-12-31": -347206000.0,
            "2021-12-31": -152734000.0,
            "2020-12-31": NaN
        },
        "Operating Cash Flow": {
            "2024-12-31": 1725175000.0,
            "2023-12-31": 1362974000.0,
            "2022-12-31": 1835047000.0,
            "2021-12-31": 1780568000.0,
            "2020-12-31": NaN
        },
        "Cash Flow From Continuing Operating Activities": {
            "2024-12-31": 1725175000.0,
            "2023-12-31": 1362974000.0,
            "2022-12-31": 1835047000.0,
            "2021-12-31": 1780568000.0,
            "2020-12-31": NaN
        },
        "Change In Working Capital": {
            "2024-12-31": 651105000.0,
            "2023-12-31": -137286000.0,
            "2022-12-31": 675447000.0,
            "2021-12-31": 1773993000.0,
            "2020-12-31": NaN
        },
        "Change In Other Working Capital": {
            "2024-12-31": 478085000.0,
            "2023-12-31": 140917000.0,
            "2022-12-31": 359723000.0,
            "2021-12-31": 847949000.0,
            "2020-12-31": NaN
        },
        "Change In Payables And Accrued Expense": {
            "2024-12-31": 13782000.0,
            "2023-12-31": 450370000.0,
            "2022-12-31": 1028172000.0,
            "2021-12-31": 1315722000.0,
            "2020-12-31": NaN
        },
        "Change In Payable": {
            "2024-12-31": 13782000.0,
            "2023-12-31": 450370000.0,
            "2022-12-31": 1028172000.0,
            "2021-12-31": 1315722000.0,
            "2020-12-31": NaN
        },
        "Change In Account Payable": {
            "2024-12-31": 13782000.0,
            "2023-12-31": 450370000.0,
            "2022-12-31": 1028172000.0,
            "2021-12-31": 1315722000.0,
            "2020-12-31": NaN
        },
        "Change In Prepaid Assets": {
            "2024-12-31": -22192000.0,
            "2023-12-31": -202834000.0,
            "2022-12-31": -267945000.0,
            "2021-12-31": 95533000.0,
            "2020-12-31": NaN
        },
        "Change In Receivables": {
            "2024-12-31": 181430000.0,
            "2023-12-31": -525739000.0,
            "2022-12-31": -444503000.0,
            "2021-12-31": -485211000.0,
            "2020-12-31": NaN
        },
        "Changes In Account Receivables": {
            "2024-12-31": 181430000.0,
            "2023-12-31": -525739000.0,
            "2022-12-31": -444503000.0,
            "2021-12-31": -485211000.0,
            "2020-12-31": NaN
        },
        "Other Non Cash Items": {
            "2024-12-31": 73631000.0,
            "2023-12-31": 122605000.0,
            "2022-12-31": 155980000.0,
            "2021-12-31": 105048000.0,
            "2020-12-31": NaN
        },
        "Stock Based Compensation": {
            "2024-12-31": 110348000.0,
            "2023-12-31": 115959000.0,
            "2022-12-31": 110049000.0,
            "2021-12-31": 209337000.0,
            "2020-12-31": NaN
        },
        "Unrealized Gain Loss On Investment Securities": {
            "2024-12-31": -102929000.0,
            "2023-12-31": -47878000.0,
            "2022-12-31": -22638000.0,
            "2021-12-31": -15447000.0,
            "2020-12-31": NaN
        },
        "Provisionand Write Offof Assets": {
            "2024-12-31": 1002000.0,
            "2023-12-31": 78336000.0,
            "2022-12-31": 68612000.0,
            "2021-12-31": -17826000.0,
            "2020-12-31": NaN
        },
        "Deferred Tax": {
            "2024-12-31": -708570000.0,
            "2023-12-31": -44018000.0,
            "2022-12-31": 7199000.0,
            "2021-12-31": -9639000.0,
            "2020-12-31": NaN
        },
        "Deferred Income Tax": {
            "2024-12-31": -708570000.0,
            "2023-12-31": -44018000.0,
            "2022-12-31": 7199000.0,
            "2021-12-31": -9639000.0,
            "2020-12-31": NaN
        },
        "Depreciation Amortization Depletion": {
            "2024-12-31": 549923000.0,
            "2023-12-31": 516797000.0,
            "2022-12-31": 449976000.0,
            "2021-12-31": 416277000.0,
            "2020-12-31": NaN
        },
        "Depreciation And Amortization": {
            "2024-12-31": 549923000.0,
            "2023-12-31": 516797000.0,
            "2022-12-31": 449976000.0,
            "2021-12-31": 416277000.0,
            "2020-12-31": NaN
        },
        "Amortization Cash Flow": {
            "2024-12-31": 249920000.0,
            "2023-12-31": 250207000.0,
            "2022-12-31": 224206000.0,
            "2021-12-31": 193437000.0,
            "2020-12-31": NaN
        },
        "Amortization Of Intangibles": {
            "2024-12-31": 249920000.0,
            "2023-12-31": 250207000.0,
            "2022-12-31": 224206000.0,
            "2021-12-31": 193437000.0,
            "2020-12-31": NaN
        },
        "Depreciation": {
            "2024-12-31": 300003000.0,
            "2023-12-31": 266590000.0,
            "2022-12-31": 225770000.0,
            "2021-12-31": 222840000.0,
            "2020-12-31": NaN
        },
        "Operating Gains Losses": {
            "2024-12-31": 19541000.0,
            "2023-12-31": 54661000.0,
            "2022-12-31": 15839000.0,
            "2021-12-31": -72389000.0,
            "2020-12-31": NaN
        },
        "Earnings Losses From Equity Investments": {
            "2024-12-31": 32371000.0,
            "2023-12-31": 30522000.0,
            "2022-12-31": 14912000.0,
            "2021-12-31": 11189000.0,
            "2020-12-31": NaN
        },
        "Gain Loss On Investment Securities": {
            "2024-12-31": -15393000.0,
            "2023-12-31": 5635000.0,
            "2022-12-31": 927000.0,
            "2021-12-31": NaN,
            "2020-12-31": NaN
        },
        "Gain Loss On Sale Of Business": {
            "2024-12-31": NaN,
            "2023-12-31": -979000.0,
            "2022-12-31": 1357000.0,
            "2021-12-31": -83578000.0,
            "2020-12-31": 1727000.0
        },
        "Net Income From Continuing Operations": {
            "2024-12-31": 1131124000.0,
            "2023-12-31": 703798000.0,
            "2022-12-31": 374583000.0,
            "2021-12-31": -608786000.0,
            "2020-12-31": NaN
        }
    }
}