{
    "info": {
        "address1": "2355 West Chandler Boulevard",
        "city": "Chandler",
        "state": "AZ",
        "zip": "85224-6199",
        "country": "United States",
        "phone": "480 792 7200",
        "website": "https://www.microchip.com",
        "industry": "Semiconductors",
        "industryKey": "semiconductors",
        "industryDisp": "Semiconductors",
        "sector": "Technology",
        "sectorKey": "technology",
        "sectorDisp": "Technology",
        "longBusinessSummary": "Microchip Technology Incorporated develops, manufactures, and sells smart, connected, and secure embedded control solutions in the Americas, Europe, and Asia. It operates through two segments, Semiconductor Products and Technology Licensing. The company offers general purpose 8-bit, 16-bit, 32-bit, and 64-bit mixed-signal microcontrollers; 32-bit and 64-bit embedded mixed-signal microprocessors; and specialized mixed-signal microcontrollers for automotive, industrial, computing, communications, lighting, power supplies, motor control, human machine interface, security, wired connectivity, and wireless connectivity applications. It also provides analog products, including power management, linear, mixed-signal, high voltage, thermal management, discrete diodes and MOSFETS, radio frequency (RF), drivers, safety, security, timing, USB, ethernet, wireless, and other interface products; field-programmable gate array (FPGA) products; and application development tools that enable system designers to program mixed-signal microcontroller, FPGA, and microprocessor products. In addition, the company offers memory products that consist of serial electrically erasable programmable read only memory (EEPROMs), serial flash memories, parallel flash memories, serial static random-access memory (SRAM), and electrically erasable random-access memory (EERAMs) for production of footprint devices; and licenses its SuperFlash embedded flash and non-volatile memory technologies to foundries, integrated device manufacturers, and design partners for use in the manufacture of microcontroller products, gate array, RF, analog, and neuromorphic compute products, as well as provides engineering services. Further, it provides wafer foundry and assembly, and test subcontracting manufacturing services; and timing systems, application specific integrated circuits, and products for aerospace applications. The company was incorporated in 1989 and is headquartered in Chandler, Arizona.",
        "fullTimeEmployees": 19400,
        "companyOfficers": [
            {
                "maxAge": 1,
                "name": "Mr. Stephen  Sanghi",
                "age": 68,
                "title": "CEO, President & Chair of the Board",
                "yearBorn": 1956,
                "fiscalYear": 2025,
                "totalPay": 452880,
                "exercisedValue": 0,
                "unexercisedValue": 0
            },
            {
                "maxAge": 1,
                "name": "Mr. James Eric Bjornholt",
                "age": 53,
                "title": "Senior Corporate Vice President & CFO",
                "yearBorn": 1971,
                "fiscalYear": 2025,
                "totalPay": 270332,
                "exercisedValue": 0,
                "unexercisedValue": 0
            },
            {
                "maxAge": 1,
                "name": "Mr. Richard J. Simoncic",
                "age": 60,
                "title": "Chief Operating Officer",
                "yearBorn": 1964,
                "fiscalYear": 2025,
                "totalPay": 289356,
                "exercisedValue": 0,
                "unexercisedValue": 0
            },
            {
                "maxAge": 1,
                "name": "Mr. Mathew B. Bunker",
                "age": 54,
                "title": "Senior Corporate Vice President of Operations",
                "yearBorn": 1970,
                "fiscalYear": 2025,
                "totalPay": 236855,
                "exercisedValue": 0,
                "unexercisedValue": 0
            },
            {
                "maxAge": 1,
                "name": "Mr. Joseph R. Krawczyk II",
                "age": 64,
                "title": "Senior Corporate Vice President of Worldwide Client Engagement",
                "yearBorn": 1960,
                "fiscalYear": 2025,
                "totalPay": 251667,
                "exercisedValue": 0,
                "unexercisedValue": 0
            },
            {
                "maxAge": 1,
                "name": "Mr. Sajid  Daudi",
                "title": "Head of Investor Relations",
                "fiscalYear": 2025,
                "exercisedValue": 0,
                "unexercisedValue": 0
            },
            {
                "maxAge": 1,
                "name": "Ms. Lauren A. Carr",
                "title": "Senior Corporate Vice President of Global Human Resources",
                "fiscalYear": 2025,
                "exercisedValue": 0,
                "unexercisedValue": 0
            },
            {
                "maxAge": 1,
                "name": "Mr. Michael A. Finley",
                "title": "Senior Corporate Vice President of Operations",
                "fiscalYear": 2025,
                "exercisedValue": 0,
                "unexercisedValue": 0
            },
            {
                "maxAge": 1,
                "name": "Mr. Patrick F. Johnson",
                "title": "Senior Corporate Vice President, FPGA & Timing Business Units",
                "fiscalYear": 2025,
                "exercisedValue": 0,
                "unexercisedValue": 0
            },
            {
                "maxAge": 1,
                "name": "Mr. David  Sadler",
                "title": "VP of Finance & Corporate Controller",
                "fiscalYear": 2025,
                "exercisedValue": 0,
                "unexercisedValue": 0
            }
        ],
        "auditRisk": 5,
        "boardRisk": 9,
        "compensationRisk": 10,
        "shareHolderRightsRisk": 2,
        "overallRisk": 9,
        "governanceEpochDate": 1759276800,
        "compensationAsOfEpochDate": 1767139200,
        "irWebsite": "http://www.microchip.com/investorshome.aspx",
        "executiveTeam": [],
        "maxAge": 86400,
        "priceHint": 2,
        "previousClose": 66.92,
        "open": 66.7,
        "dayLow": 65.08,
        "dayHigh": 66.74,
        "regularMarketPreviousClose": 66.92,
        "regularMarketOpen": 65.32,
        "regularMarketDayLow": 65.08,
        "regularMarketDayHigh": 66.74,
        "dividendRate": 1.82,
        "dividendYield": 2.72,
        "exDividendDate": 1755820800,
        "payoutRatio": 3.1772,
        "fiveYearAvgDividendYield": 1.8,
        "beta": 1.535,
        "forwardPE": 25.046156,
        "volume": 1843916,
        "regularMarketVolume": 1843848,
        "averageVolume": 8117045,
        "averageVolume10days": 6251490,
        "averageDailyVolume10Day": 6251490,
        "bid": 65.0,
        "ask": 69.26,
        "bidSize": 30,
        "askSize": 1,
        "marketCap": 35143942144,
        "fiftyTwoWeekLow": 34.13,
        "fiftyTwoWeekHigh": 79.44,
        "allTimeHigh": 100.57,
        "allTimeLow": 0.310014,
        "priceToSalesTrailing12Months": 8.296885,
        "fiftyDayAverage": 65.5156,
        "twoHundredDayAverage": 59.71105,
        "trailingAnnualDividendRate": 1.819,
        "trailingAnnualDividendYield": 0.027181711,
        "currency": "USD",
        "tradeable": false,
        "enterpriseValue": 41043361792,
        "profitMargins": -0.03503,
        "floatShares": 527914650,
        "sharesOutstanding": 539679667,
        "sharesShort": 22502833,
        "sharesShortPriorMonth": 23837554,
        "sharesShortPreviousMonthDate": 1755216000,
        "dateShortInterest": 1757894400,
        "sharesPercentSharesOut": 0.0417,
        "heldPercentInsiders": 0.02101,
        "heldPercentInstitutions": 1.05519,
        "shortRatio": 2.97,
        "shortPercentOfFloat": 0.048600003,
        "impliedSharesOutstanding": 539679667,
        "bookValue": 12.706,
        "priceToBook": 5.125138,
        "lastFiscalYearEnd": 1743379200,
        "nextFiscalYearEnd": 1774915200,
        "mostRecentQuarter": 1751241600,
        "netIncomeToCommon": -178400000,
        "trailingEps": -0.34,
        "forwardEps": 2.6,
        "lastSplitFactor": "2:1",
        "lastSplitDate": 1634083200,
        "enterpriseToRevenue": 9.69,
        "enterpriseToEbitda": 43.635,
        "52WeekChange": -0.13472974,
        "SandP52WeekChange": 0.16845357,
        "lastDividendValue": 0.455,
        "lastDividendDate": 1755820800,
        "quoteType": "EQUITY",
        "currentPrice": 65.12,
        "targetHighPrice": 90.0,
        "targetLowPrice": 60.0,
        "targetMeanPrice": 76.0,
        "targetMedianPrice": 77.0,
        "recommendationMean": 1.73077,
        "recommendationKey": "buy",
        "numberOfAnalystOpinions": 25,
        "totalCash": 566499968,
        "totalCashPerShare": 1.05,
        "ebitda": 940600000,
        "totalDebt": 5494499840,
        "quickRatio": 1.119,
        "currentRatio": 2.313,
        "totalRevenue": 4235800064,
        "debtToEquity": 80.129,
        "revenuePerShare": 7.874,
        "returnOnAssets": 0.00844,
        "returnOnEquity": -0.02238,
        "grossProfits": 2307699968,
        "freeCashflow": 993012480,
        "operatingCashflow": 796600000,
        "revenueGrowth": -0.134,
        "grossMargins": 0.54481,
        "ebitdaMargins": 0.22206,
        "operatingMargins": 0.05049,
        "financialCurrency": "USD",
        "symbol": "MCHP",
        "language": "en-US",
        "region": "US",
        "typeDisp": "Equity",
        "quoteSourceName": "Nasdaq Real Time Price",
        "triggerable": true,
        "customPriceAlertConfidence": "HIGH",
        "earningsTimestamp": 1754596800,
        "earningsTimestampStart": 1762804800,
        "earningsTimestampEnd": 1762804800,
        "earningsCallTimestampStart": 1754600400,
        "earningsCallTimestampEnd": 1754600400,
        "isEarningsDateEstimate": true,
        "epsTrailingTwelveMonths": -0.34,
        "epsForward": 2.6,
        "epsCurrentYear": 1.45795,
        "priceEpsCurrentYear": 44.66546,
        "fiftyDayAverageChange": -0.39559937,
        "fiftyDayAverageChangePercent": -0.0060382467,
        "twoHundredDayAverageChange": 5.4089546,
        "twoHundredDayAverageChangePercent": 0.09058549,
        "sourceInterval": 15,
        "exchangeDataDelayedBy": 0,
        "averageAnalystRating": "1.7 - Buy",
        "cryptoTradeable": false,
        "shortName": "Microchip Technology Incorporat",
        "longName": "Microchip Technology Incorporated",
        "regularMarketTime": 1760037459,
        "exchange": "NMS",
        "messageBoardId": "finmb_31500",
        "exchangeTimezoneName": "America/New_York",
        "exchangeTimezoneShortName": "EDT",
        "gmtOffSetMilliseconds": -14400000,
        "market": "us_market",
        "esgPopulated": false,
        "regularMarketChangePercent": -2.6897721,
        "regularMarketPrice": 65.12,
        "corporateActions": [],
        "marketState": "REGULAR",
        "hasPrePostMarketData": true,
        "firstTradeDateMilliseconds": 732551400000,
        "regularMarketChange": -1.7999954,
        "regularMarketDayRange": "65.08 - 66.74",
        "fullExchangeName": "NasdaqGS",
        "averageDailyVolume3Month": 8117045,
        "fiftyTwoWeekLowChange": 30.990002,
        "fiftyTwoWeekLowChangePercent": 0.90799886,
        "fiftyTwoWeekRange": "34.13 - 79.44",
        "fiftyTwoWeekHighChange": -14.32,
        "fiftyTwoWeekHighChangePercent": -0.18026182,
        "fiftyTwoWeekChangePercent": -13.472975,
        "dividendDate": 1757030400,
        "trailingPegRatio": null
    },
    "income_statement": {
        "Tax Effect Of Unusual Items": {
            "2025-03-31": -16989000.0,
            "2024-03-31": 19400.650915,
            "2023-03-31": -993092.071348,
            "2022-03-31": -18989072.512648,
            "2021-03-31": NaN
        },
        "Tax Rate For Calcs": {
            "2025-03-31": 0.21,
            "2024-03-31": 0.194007,
            "2023-03-31": 0.230952,
            "2022-03-31": 0.132884,
            "2021-03-31": NaN
        },
        "Normalized EBITDA": {
            "2025-03-31": 1121300000.0,
            "2024-03-31": 3436300000.0,
            "2023-03-31": 4106800000.0,
            "2022-03-31": 3014400000.0,
            "2021-03-31": NaN
        },
        "Total Unusual Items": {
            "2025-03-31": -80900000.0,
            "2024-03-31": 100000.0,
            "2023-03-31": -4300000.0,
            "2022-03-31": -142900000.0,
            "2021-03-31": NaN
        },
        "Total Unusual Items Excluding Goodwill": {
            "2025-03-31": -80900000.0,
            "2024-03-31": 100000.0,
            "2023-03-31": -4300000.0,
            "2022-03-31": -142900000.0,
            "2021-03-31": NaN
        },
        "Net Income From Continuing Operation Net Minority Interest": {
            "2025-03-31": -500000.0,
            "2024-03-31": 1906900000.0,
            "2023-03-31": 2237700000.0,
            "2022-03-31": 1285500000.0,
            "2021-03-31": NaN
        },
        "Reconciled Depreciation": {
            "2025-03-31": 750100000.0,
            "2024-03-31": 879500000.0,
            "2023-03-31": 998400000.0,
            "2022-03-31": 1143500000.0,
            "2021-03-31": NaN
        },
        "Reconciled Cost Of Revenue": {
            "2025-03-31": 1674500000.0,
            "2024-03-31": 2364600000.0,
            "2023-03-31": 2412300000.0,
            "2022-03-31": 2090300000.0,
            "2021-03-31": NaN
        },
        "EBITDA": {
            "2025-03-31": 1040400000.0,
            "2024-03-31": 3436400000.0,
            "2023-03-31": 4102500000.0,
            "2022-03-31": 2871500000.0,
            "2021-03-31": NaN
        },
        "EBIT": {
            "2025-03-31": 290300000.0,
            "2024-03-31": 2556900000.0,
            "2023-03-31": 3104100000.0,
            "2022-03-31": 1728000000.0,
            "2021-03-31": NaN
        },
        "Net Interest Income": {
            "2025-03-31": -250000000.0,
            "2024-03-31": -190700000.0,
            "2023-03-31": -201800000.0,
            "2022-03-31": -256500000.0,
            "2021-03-31": NaN
        },
        "Interest Expense": {
            "2025-03-31": 251400000.0,
            "2024-03-31": 191000000.0,
            "2023-03-31": 194400000.0,
            "2022-03-31": 245500000.0,
            "2021-03-31": NaN
        },
        "Interest Income": {
            "2025-03-31": 9200000.0,
            "2024-03-31": 7600000.0,
            "2023-03-31": 2100000.0,
            "2022-03-31": 500000.0,
            "2021-03-31": NaN
        },
        "Normalized Income": {
            "2025-03-31": 63411000.0,
            "2024-03-31": 1906819400.650915,
            "2023-03-31": 2241006907.928652,
            "2022-03-31": 1409410927.487352,
            "2021-03-31": NaN
        },
        "Net Income From Continuing And Discontinued Operation": {
            "2025-03-31": -500000.0,
            "2024-03-31": 1906900000.0,
            "2023-03-31": 2237700000.0,
            "2022-03-31": 1285500000.0,
            "2021-03-31": NaN
        },
        "Total Expenses": {
            "2025-03-31": 4026100000.0,
            "2024-03-31": 5075700000.0,
            "2023-03-31": 5326700000.0,
            "2022-03-31": 4941800000.0,
            "2021-03-31": NaN
        },
        "Total Operating Income As Reported": {
            "2025-03-31": 296300000.0,
            "2024-03-31": 2571000000.0,
            "2023-03-31": 3116000000.0,
            "2022-03-31": 1849600000.0,
            "2021-03-31": NaN
        },
        "Diluted Average Shares": {
            "2025-03-31": 537300000.0,
            "2024-03-31": 548000000.0,
            "2023-03-31": 557300000.0,
            "2022-03-31": 565900000.0,
            "2021-03-31": NaN
        },
        "Basic Average Shares": {
            "2025-03-31": 537300000.0,
            "2024-03-31": 542000000.0,
            "2023-03-31": 550400000.0,
            "2022-03-31": 552300000.0,
            "2021-03-31": NaN
        },
        "Diluted EPS": {
            "2025-03-31": -0.01,
            "2024-03-31": 3.48,
            "2023-03-31": 4.02,
            "2022-03-31": 2.27,
            "2021-03-31": NaN
        },
        "Basic EPS": {
            "2025-03-31": -0.01,
            "2024-03-31": 3.52,
            "2023-03-31": 4.07,
            "2022-03-31": 2.33,
            "2021-03-31": NaN
        },
        "Diluted NI Availto Com Stockholders": {
            "2025-03-31": -2700000.0,
            "2024-03-31": 1906900000.0,
            "2023-03-31": 2237700000.0,
            "2022-03-31": 1285500000.0,
            "2021-03-31": NaN
        },
        "Net Income Common Stockholders": {
            "2025-03-31": -2700000.0,
            "2024-03-31": 1906900000.0,
            "2023-03-31": 2237700000.0,
            "2022-03-31": 1285500000.0,
            "2021-03-31": NaN
        },
        "Preferred Stock Dividends": {
            "2025-03-31": 2200000.0,
            "2024-03-31": NaN,
            "2023-03-31": NaN,
            "2022-03-31": NaN,
            "2021-03-31": NaN
        },
        "Net Income": {
            "2025-03-31": -500000.0,
            "2024-03-31": 1906900000.0,
            "2023-03-31": 2237700000.0,
            "2022-03-31": 1285500000.0,
            "2021-03-31": NaN
        },
        "Net Income Including Noncontrolling Interests": {
            "2025-03-31": -500000.0,
            "2024-03-31": 1906900000.0,
            "2023-03-31": 2237700000.0,
            "2022-03-31": 1285500000.0,
            "2021-03-31": NaN
        },
        "Net Income Continuous Operations": {
            "2025-03-31": -500000.0,
            "2024-03-31": 1906900000.0,
            "2023-03-31": 2237700000.0,
            "2022-03-31": 1285500000.0,
            "2021-03-31": NaN
        },
        "Tax Provision": {
            "2025-03-31": 39400000.0,
            "2024-03-31": 459000000.0,
            "2023-03-31": 672000000.0,
            "2022-03-31": 197000000.0,
            "2021-03-31": NaN
        },
        "Pretax Income": {
            "2025-03-31": 38900000.0,
            "2024-03-31": 2365900000.0,
            "2023-03-31": 2909700000.0,
            "2022-03-31": 1482500000.0,
            "2021-03-31": NaN
        },
        "Other Income Expense": {
            "2025-03-31": -86600000.0,
            "2024-03-31": -2100000.0,
            "2023-03-31": -500000.0,
            "2022-03-31": -140100000.0,
            "2021-03-31": NaN
        },
        "Other Non Operating Income Expenses": {
            "2025-03-31": -5700000.0,
            "2024-03-31": -2200000.0,
            "2023-03-31": 3800000.0,
            "2022-03-31": 2800000.0,
            "2021-03-31": NaN
        },
        "Special Income Charges": {
            "2025-03-31": -80900000.0,
            "2024-03-31": 100000.0,
            "2023-03-31": -4300000.0,
            "2022-03-31": -142900000.0,
            "2021-03-31": NaN
        },
        "Other Special Charges": {
            "2025-03-31": 4400000.0,
            "2024-03-31": -6300000.0,
            "2023-03-31": -10300000.0,
            "2022-03-31": 142900000.0,
            "2021-03-31": NaN
        },
        "Restructuring And Mergern Acquisition": {
            "2025-03-31": 76500000.0,
            "2024-03-31": 6200000.0,
            "2023-03-31": 14600000.0,
            "2022-03-31": 17000000.0,
            "2021-03-31": NaN
        },
        "Earnings From Equity Interest": {
            "2025-03-31": NaN,
            "2024-03-31": NaN,
            "2023-03-31": NaN,
            "2022-03-31": NaN,
            "2021-03-31": 0.0
        },
        "Net Non Operating Interest Income Expense": {
            "2025-03-31": -250000000.0,
            "2024-03-31": -190700000.0,
            "2023-03-31": -201800000.0,
            "2022-03-31": -256500000.0,
            "2021-03-31": NaN
        },
        "Total Other Finance Cost": {
            "2025-03-31": 7800000.0,
            "2024-03-31": 7300000.0,
            "2023-03-31": 9500000.0,
            "2022-03-31": 11500000.0,
            "2021-03-31": NaN
        },
        "Interest Expense Non Operating": {
            "2025-03-31": 251400000.0,
            "2024-03-31": 191000000.0,
            "2023-03-31": 194400000.0,
            "2022-03-31": 245500000.0,
            "2021-03-31": NaN
        },
        "Interest Income Non Operating": {
            "2025-03-31": 9200000.0,
            "2024-03-31": 7600000.0,
            "2023-03-31": 2100000.0,
            "2022-03-31": 500000.0,
            "2021-03-31": NaN
        },
        "Operating Income": {
            "2025-03-31": 375500000.0,
            "2024-03-31": 2558700000.0,
            "2023-03-31": 3112000000.0,
            "2022-03-31": 1879100000.0,
            "2021-03-31": NaN
        },
        "Operating Expense": {
            "2025-03-31": 2092400000.0,
            "2024-03-31": 2437000000.0,
            "2023-03-31": 2585900000.0,
            "2022-03-31": 2570500000.0,
            "2021-03-31": NaN
        },
        "Depreciation Amortization Depletion Income Statement": {
            "2025-03-31": 490900000.0,
            "2024-03-31": 605400000.0,
            "2023-03-31": 669900000.0,
            "2022-03-31": 862500000.0,
            "2021-03-31": NaN
        },
        "Depreciation And Amortization In Income Statement": {
            "2025-03-31": 490900000.0,
            "2024-03-31": 605400000.0,
            "2023-03-31": 669900000.0,
            "2022-03-31": 862500000.0,
            "2021-03-31": NaN
        },
        "Amortization": {
            "2025-03-31": 490900000.0,
            "2024-03-31": 605400000.0,
            "2023-03-31": 669900000.0,
            "2022-03-31": 862500000.0,
            "2021-03-31": NaN
        },
        "Amortization Of Intangibles Income Statement": {
            "2025-03-31": 490900000.0,
            "2024-03-31": 605400000.0,
            "2023-03-31": 669900000.0,
            "2022-03-31": 862500000.0,
            "2021-03-31": NaN
        },
        "Research And Development": {
            "2025-03-31": 983800000.0,
            "2024-03-31": 1097400000.0,
            "2023-03-31": 1118300000.0,
            "2022-03-31": 989100000.0,
            "2021-03-31": NaN
        },
        "Selling General And Administration": {
            "2025-03-31": 617700000.0,
            "2024-03-31": 734200000.0,
            "2023-03-31": 797700000.0,
            "2022-03-31": 718900000.0,
            "2021-03-31": NaN
        },
        "Gross Profit": {
            "2025-03-31": 2467900000.0,
            "2024-03-31": 4995700000.0,
            "2023-03-31": 5697900000.0,
            "2022-03-31": 4449600000.0,
            "2021-03-31": NaN
        },
        "Cost Of Revenue": {
            "2025-03-31": 1933700000.0,
            "2024-03-31": 2638700000.0,
            "2023-03-31": 2740800000.0,
            "2022-03-31": 2371300000.0,
            "2021-03-31": NaN
        },
        "Total Revenue": {
            "2025-03-31": 4401600000.0,
            "2024-03-31": 7634400000.0,
            "2023-03-31": 8438700000.0,
            "2022-03-31": 6820900000.0,
            "2021-03-31": NaN
        },
        "Operating Revenue": {
            "2025-03-31": 4401600000.0,
            "2024-03-31": 7634400000.0,
            "2023-03-31": 8438700000.0,
            "2022-03-31": 6820900000.0,
            "2021-03-31": NaN
        }
    },
    "balance_sheet": {
        "Treasury Shares Number": {
            "2025-03-31": 39292311.0,
            "2024-03-31": 41142968.0,
            "2023-03-31": 32345809.0,
            "2022-03-31": 23304872.0,
            "2021-03-31": NaN
        },
        "Ordinary Shares Number": {
            "2025-03-31": 538704604.0,
            "2024-03-31": 536663691.0,
            "2023-03-31": 545459814.0,
            "2022-03-31": 554500524.0,
            "2021-03-31": NaN
        },
        "Share Issued": {
            "2025-03-31": 577996915.0,
            "2024-03-31": 577806659.0,
            "2023-03-31": 577805623.0,
            "2022-03-31": 577805396.0,
            "2021-03-31": NaN
        },
        "Net Debt": {
            "2025-03-31": 4858700000.0,
            "2024-03-31": 5680100000.0,
            "2023-03-31": 6205900000.0,
            "2022-03-31": 7370000000.0,
            "2021-03-31": NaN
        },
        "Total Debt": {
            "2025-03-31": 5666100000.0,
            "2024-03-31": 6032400000.0,
            "2023-03-31": 6471400000.0,
            "2022-03-31": 7721200000.0,
            "2021-03-31": NaN
        },
        "Tangible Book Value": {
            "2025-03-31": -1995500000.0,
            "2024-03-31": -2799400000.0,
            "2023-03-31": -3529000000.0,
            "2022-03-31": -4821900000.0,
            "2021-03-31": NaN
        },
        "Invested Capital": {
            "2025-03-31": 12708700000.0,
            "2024-03-31": 12657600000.0,
            "2023-03-31": 12953500000.0,
            "2022-03-31": 13582200000.0,
            "2021-03-31": NaN
        },
        "Working Capital": {
            "2025-03-31": 1836200000.0,
            "2024-03-31": 493600000.0,
            "2023-03-31": -49300000.0,
            "2022-03-31": 1053600000.0,
            "2021-03-31": NaN
        },
        "Net Tangible Assets": {
            "2025-03-31": -1995500000.0,
            "2024-03-31": -2799400000.0,
            "2023-03-31": -3529000000.0,
            "2022-03-31": -4821900000.0,
            "2021-03-31": NaN
        },
        "Capital Lease Obligations": {
            "2025-03-31": 35700000.0,
            "2024-03-31": 32600000.0,
            "2023-03-31": 31500000.0,
            "2022-03-31": 33800000.0,
            "2021-03-31": NaN
        },
        "Common Stock Equity": {
            "2025-03-31": 7078300000.0,
            "2024-03-31": 6657800000.0,
            "2023-03-31": 6513600000.0,
            "2022-03-31": 5894800000.0,
            "2021-03-31": NaN
        },
        "Total Capitalization": {
            "2025-03-31": 12708700000.0,
            "2024-03-31": 11658200000.0,
            "2023-03-31": 11555300000.0,
            "2022-03-31": 13582200000.0,
            "2021-03-31": NaN
        },
        "Total Equity Gross Minority Interest": {
            "2025-03-31": 7078300000.0,
            "2024-03-31": 6657800000.0,
            "2023-03-31": 6513600000.0,
            "2022-03-31": 5894800000.0,
            "2021-03-31": NaN
        },
        "Stockholders Equity": {
            "2025-03-31": 7078300000.0,
            "2024-03-31": 6657800000.0,
            "2023-03-31": 6513600000.0,
            "2022-03-31": 5894800000.0,
            "2021-03-31": NaN
        },
        "Gains Losses Not Affecting Retained Earnings": {
            "2025-03-31": -1700000.0,
            "2024-03-31": -3500000.0,
            "2023-03-31": -4100000.0,
            "2022-03-31": -20600000.0,
            "2021-03-31": NaN
        },
        "Other Equity Adjustments": {
            "2025-03-31": -1700000.0,
            "2024-03-31": -3500000.0,
            "2023-03-31": -4100000.0,
            "2022-03-31": -20600000.0,
            "2021-03-31": NaN
        },
        "Treasury Stock": {
            "2025-03-31": 2611600000.0,
            "2024-03-31": 2581600000.0,
            "2023-03-31": 1660200000.0,
            "2022-03-31": 796300000.0,
            "2021-03-31": NaN
        },
        "Retained Earnings": {
            "2025-03-31": 5781100000.0,
            "2024-03-31": 6759500000.0,
            "2023-03-31": 5764100000.0,
            "2022-03-31": 4175200000.0,
            "2021-03-31": NaN
        },
        "Additional Paid In Capital": {
            "2025-03-31": 3909900000.0,
            "2024-03-31": 2482900000.0,
            "2023-03-31": 2413300000.0,
            "2022-03-31": 2535900000.0,
            "2021-03-31": NaN
        },
        "Capital Stock": {
            "2025-03-31": 600000.0,
            "2024-03-31": 500000.0,
            "2023-03-31": 500000.0,
            "2022-03-31": 600000.0,
            "2021-03-31": NaN
        },
        "Common Stock": {
            "2025-03-31": 600000.0,
            "2024-03-31": 500000.0,
            "2023-03-31": 500000.0,
            "2022-03-31": 600000.0,
            "2021-03-31": NaN
        },
        "Preferred Stock": {
            "2025-03-31": 0.0,
            "2024-03-31": 0.0,
            "2023-03-31": 0.0,
            "2022-03-31": 0.0,
            "2021-03-31": NaN
        },
        "Total Liabilities Net Minority Interest": {
            "2025-03-31": 8296300000.0,
            "2024-03-31": 9215400000.0,
            "2023-03-31": 9856700000.0,
            "2022-03-31": 10304700000.0,
            "2021-03-31": NaN
        },
        "Total Non Current Liabilities Net Minority Interest": {
            "2025-03-31": 7141200000.0,
            "2024-03-31": 6696000000.0,
            "2023-03-31": 6738100000.0,
            "2022-03-31": 8905700000.0,
            "2021-03-31": NaN
        },
        "Other Non Current Liabilities": {
            "2025-03-31": 843600000.0,
            "2024-03-31": 1017600000.0,
            "2023-03-31": 948000000.0,
            "2022-03-31": 473900000.0,
            "2021-03-31": NaN
        },
        "Tradeand Other Payables Non Current": {
            "2025-03-31": 633400000.0,
            "2024-03-31": 649200000.0,
            "2023-03-31": 705700000.0,
            "2022-03-31": 704600000.0,
            "2021-03-31": NaN
        },
        "Non Current Deferred Liabilities": {
            "2025-03-31": 33800000.0,
            "2024-03-31": 28800000.0,
            "2023-03-31": 42700000.0,
            "2022-03-31": 39800000.0,
            "2021-03-31": NaN
        },
        "Non Current Deferred Taxes Liabilities": {
            "2025-03-31": 33800000.0,
            "2024-03-31": 28800000.0,
            "2023-03-31": 42700000.0,
            "2022-03-31": 39800000.0,
            "2021-03-31": NaN
        },
        "Long Term Debt And Capital Lease Obligation": {
            "2025-03-31": 5630400000.0,
            "2024-03-31": 5000400000.0,
            "2023-03-31": 5041700000.0,
            "2022-03-31": 7687400000.0,
            "2021-03-31": NaN
        },
        "Long Term Capital Lease Obligation": {
            "2025-03-31": NaN,
            "2024-03-31": NaN,
            "2023-03-31": 128600000.0,
            "2022-03-31": 128600000.0,
            "2021-03-31": 125400000.0
        },
        "Long Term Debt": {
            "2025-03-31": 5630400000.0,
            "2024-03-31": 5000400000.0,
            "2023-03-31": 5041700000.0,
            "2022-03-31": 7687400000.0,
            "2021-03-31": NaN
        },
        "Current Liabilities": {
            "2025-03-31": 1155100000.0,
            "2024-03-31": 2519400000.0,
            "2023-03-31": 3118600000.0,
            "2022-03-31": 1399000000.0,
            "2021-03-31": NaN
        },
        "Current Deferred Liabilities": {
            "2025-03-31": 213400000.0,
            "2024-03-31": 261800000.0,
            "2023-03-31": 121400000.0,
            "2022-03-31": 73200000.0,
            "2021-03-31": NaN
        },
        "Current Deferred Revenue": {
            "2025-03-31": 213400000.0,
            "2024-03-31": 261800000.0,
            "2023-03-31": 121400000.0,
            "2022-03-31": 73200000.0,
            "2021-03-31": NaN
        },
        "Current Debt And Capital Lease Obligation": {
            "2025-03-31": 35700000.0,
            "2024-03-31": 1032000000.0,
            "2023-03-31": 1429700000.0,
            "2022-03-31": 33800000.0,
            "2021-03-31": NaN
        },
        "Current Capital Lease Obligation": {
            "2025-03-31": 35700000.0,
            "2024-03-31": 32600000.0,
            "2023-03-31": 31500000.0,
            "2022-03-31": 33800000.0,
            "2021-03-31": NaN
        },
        "Current Debt": {
            "2025-03-31": NaN,
            "2024-03-31": 999400000.0,
            "2023-03-31": 1398200000.0,
            "2022-03-31": NaN,
            "2021-03-31": 1322900000.0
        },
        "Other Current Borrowings": {
            "2025-03-31": NaN,
            "2024-03-31": 999400000.0,
            "2023-03-31": 1398200000.0,
            "2022-03-31": NaN,
            "2021-03-31": 1322900000.0
        },
        "Pensionand Other Post Retirement Benefit Plans Current": {
            "2025-03-31": 108100000.0,
            "2024-03-31": 117800000.0,
            "2023-03-31": 193500000.0,
            "2022-03-31": 213700000.0,
            "2021-03-31": NaN
        },
        "Current Provisions": {
            "2025-03-31": 329700000.0,
            "2024-03-31": 580600000.0,
            "2023-03-31": 536100000.0,
            "2022-03-31": 334900000.0,
            "2021-03-31": NaN
        },
        "Payables And Accrued Expenses": {
            "2025-03-31": 468200000.0,
            "2024-03-31": 527200000.0,
            "2023-03-31": 837900000.0,
            "2022-03-31": 743400000.0,
            "2021-03-31": NaN
        },
        "Current Accrued Expenses": {
            "2025-03-31": 208500000.0,
            "2024-03-31": 223400000.0,
            "2023-03-31": 334800000.0,
            "2022-03-31": 277200000.0,
            "2021-03-31": NaN
        },
        "Payables": {
            "2025-03-31": 259700000.0,
            "2024-03-31": 303800000.0,
            "2023-03-31": 503100000.0,
            "2022-03-31": 466200000.0,
            "2021-03-31": NaN
        },
        "Total Tax Payable": {
            "2025-03-31": 99100000.0,
            "2024-03-31": 90800000.0,
            "2023-03-31": 106200000.0,
            "2022-03-31": 121500000.0,
            "2021-03-31": NaN
        },
        "Income Tax Payable": {
            "2025-03-31": 99100000.0,
            "2024-03-31": 90800000.0,
            "2023-03-31": 106200000.0,
            "2022-03-31": 121500000.0,
            "2021-03-31": NaN
        },
        "Accounts Payable": {
            "2025-03-31": 160600000.0,
            "2024-03-31": 213000000.0,
            "2023-03-31": 396900000.0,
            "2022-03-31": 344700000.0,
            "2021-03-31": NaN
        },
        "Total Assets": {
            "2025-03-31": 15374600000.0,
            "2024-03-31": 15873200000.0,
            "2023-03-31": 16370300000.0,
            "2022-03-31": 16199500000.0,
            "2021-03-31": NaN
        },
        "Total Non Current Assets": {
            "2025-03-31": 12383300000.0,
            "2024-03-31": 12860200000.0,
            "2023-03-31": 13301000000.0,
            "2022-03-31": 13746900000.0,
            "2021-03-31": NaN
        },
        "Other Non Current Assets": {
            "2025-03-31": 397700000.0,
            "2024-03-31": 611900000.0,
            "2023-03-31": 457200000.0,
            "2022-03-31": 265200000.0,
            "2021-03-31": NaN
        },
        "Non Current Deferred Assets": {
            "2025-03-31": 1728100000.0,
            "2024-03-31": 1596500000.0,
            "2023-03-31": 1623300000.0,
            "2022-03-31": 1797100000.0,
            "2021-03-31": NaN
        },
        "Non Current Deferred Taxes Assets": {
            "2025-03-31": 1728100000.0,
            "2024-03-31": 1596500000.0,
            "2023-03-31": 1623300000.0,
            "2022-03-31": 1797100000.0,
            "2021-03-31": NaN
        },
        "Goodwill And Other Intangible Assets": {
            "2025-03-31": 9073800000.0,
            "2024-03-31": 9457200000.0,
            "2023-03-31": 10042600000.0,
            "2022-03-31": 10716700000.0,
            "2021-03-31": NaN
        },
        "Other Intangible Assets": {
            "2025-03-31": 2389000000.0,
            "2024-03-31": 2781800000.0,
            "2023-03-31": 3369000000.0,
            "2022-03-31": 4043100000.0,
            "2021-03-31": NaN
        },
        "Goodwill": {
            "2025-03-31": 6684800000.0,
            "2024-03-31": 6675400000.0,
            "2023-03-31": 6673600000.0,
            "2022-03-31": 6673600000.0,
            "2021-03-31": NaN
        },
        "Net PPE": {
            "2025-03-31": 1183700000.0,
            "2024-03-31": 1194600000.0,
            "2023-03-31": 1177900000.0,
            "2022-03-31": 967900000.0,
            "2021-03-31": NaN
        },
        "Accumulated Depreciation": {
            "2025-03-31": -2342400000.0,
            "2024-03-31": -2818700000.0,
            "2023-03-31": -2651200000.0,
            "2022-03-31": -2448700000.0,
            "2021-03-31": NaN
        },
        "Gross PPE": {
            "2025-03-31": 3526100000.0,
            "2024-03-31": 4013300000.0,
            "2023-03-31": 3829100000.0,
            "2022-03-31": 3416600000.0,
            "2021-03-31": NaN
        },
        "Construction In Progress": {
            "2025-03-31": 424100000.0,
            "2024-03-31": 349600000.0,
            "2023-03-31": 354300000.0,
            "2022-03-31": 182400000.0,
            "2021-03-31": NaN
        },
        "Other Properties": {
            "2025-03-31": NaN,
            "2024-03-31": NaN,
            "2023-03-31": 154000000.0,
            "2022-03-31": 153300000.0,
            "2021-03-31": 154300000.0
        },
        "Machinery Furniture Equipment": {
            "2025-03-31": 2311300000.0,
            "2024-03-31": 2778100000.0,
            "2023-03-31": 2669100000.0,
            "2022-03-31": 2471600000.0,
            "2021-03-31": NaN
        },
        "Buildings And Improvements": {
            "2025-03-31": 705900000.0,
            "2024-03-31": 796300000.0,
            "2023-03-31": 716400000.0,
            "2022-03-31": 674400000.0,
            "2021-03-31": NaN
        },
        "Land And Improvements": {
            "2025-03-31": 84800000.0,
            "2024-03-31": 89300000.0,
            "2023-03-31": 89300000.0,
            "2022-03-31": 88200000.0,
            "2021-03-31": NaN
        },
        "Properties": {
            "2025-03-31": 0.0,
            "2024-03-31": 0.0,
            "2023-03-31": 0.0,
            "2022-03-31": 0.0,
            "2021-03-31": NaN
        },
        "Current Assets": {
            "2025-03-31": 2991300000.0,
            "2024-03-31": 3013000000.0,
            "2023-03-31": 3069300000.0,
            "2022-03-31": 2452600000.0,
            "2021-03-31": NaN
        },
        "Other Current Assets": {
            "2025-03-31": 236400000.0,
            "2024-03-31": 233600000.0,
            "2023-03-31": 205100000.0,
            "2022-03-31": 206200000.0,
            "2021-03-31": NaN
        },
        "Inventory": {
            "2025-03-31": 1293500000.0,
            "2024-03-31": 1316000000.0,
            "2023-03-31": 1324900000.0,
            "2022-03-31": 854400000.0,
            "2021-03-31": NaN
        },
        "Finished Goods": {
            "2025-03-31": 261100000.0,
            "2024-03-31": 334500000.0,
            "2023-03-31": 322500000.0,
            "2022-03-31": 208600000.0,
            "2021-03-31": NaN
        },
        "Work In Process": {
            "2025-03-31": 857600000.0,
            "2024-03-31": 797500000.0,
            "2023-03-31": 809800000.0,
            "2022-03-31": 482800000.0,
            "2021-03-31": NaN
        },
        "Raw Materials": {
            "2025-03-31": 174800000.0,
            "2024-03-31": 184000000.0,
            "2023-03-31": 192600000.0,
            "2022-03-31": 163000000.0,
            "2021-03-31": NaN
        },
        "Receivables": {
            "2025-03-31": 689700000.0,
            "2024-03-31": 1143700000.0,
            "2023-03-31": 1305300000.0,
            "2022-03-31": 1072600000.0,
            "2021-03-31": NaN
        },
        "Receivables Adjustments Allowances": {
            "2025-03-31": -5900000.0,
            "2024-03-31": -8100000.0,
            "2023-03-31": -8600000.0,
            "2022-03-31": -6200000.0,
            "2021-03-31": NaN
        },
        "Other Receivables": {
            "2025-03-31": 11500000.0,
            "2024-03-31": 10100000.0,
            "2023-03-31": 13500000.0,
            "2022-03-31": 9300000.0,
            "2021-03-31": NaN
        },
        "Accounts Receivable": {
            "2025-03-31": 684100000.0,
            "2024-03-31": 1141700000.0,
            "2023-03-31": 1300400000.0,
            "2022-03-31": 1069500000.0,
            "2021-03-31": NaN
        },
        "Allowance For Doubtful Accounts Receivable": {
            "2025-03-31": NaN,
            "2024-03-31": NaN,
            "2023-03-31": NaN,
            "2022-03-31": NaN,
            "2021-03-31": -5200000.0
        },
        "Gross Accounts Receivable": {
            "2025-03-31": NaN,
            "2024-03-31": NaN,
            "2023-03-31": NaN,
            "2022-03-31": NaN,
            "2021-03-31": 1002900000.0
        },
        "Cash Cash Equivalents And Short Term Investments": {
            "2025-03-31": 771700000.0,
            "2024-03-31": 319700000.0,
            "2023-03-31": 234000000.0,
            "2022-03-31": 319400000.0,
            "2021-03-31": NaN
        },
        "Other Short Term Investments": {
            "2025-03-31": NaN,
            "2024-03-31": NaN,
            "2023-03-31": 0.0,
            "2022-03-31": 2000000.0,
            "2021-03-31": 2000000.0
        },
        "Cash And Cash Equivalents": {
            "2025-03-31": 771700000.0,
            "2024-03-31": 319700000.0,
            "2023-03-31": 234000000.0,
            "2022-03-31": 317400000.0,
            "2021-03-31": NaN
        }
    },
    "cash_flow": {
        "Free Cash Flow": {
            "2025-03-31": 772100000.0,
            "2024-03-31": 2607600000.0,
            "2023-03-31": 3134800000.0,
            "2022-03-31": 2472600000.0,
            "2021-03-31": NaN
        },
        "Repurchase Of Capital Stock": {
            "2025-03-31": -96500000.0,
            "2024-03-31": -982100000.0,
            "2023-03-31": -945800000.0,
            "2022-03-31": -425600000.0,
            "2021-03-31": NaN
        },
        "Repayment Of Debt": {
            "2025-03-31": -17605700000.0,
            "2024-03-31": -17594100000.0,
            "2023-03-31": -7405300000.0,
            "2022-03-31": -6549000000.0,
            "2021-03-31": NaN
        },
        "Issuance Of Debt": {
            "2025-03-31": 17247700000.0,
            "2024-03-31": 17054800000.0,
            "2023-03-31": 5935000000.0,
            "2022-03-31": 5173000000.0,
            "2021-03-31": NaN
        },
        "Issuance Of Capital Stock": {
            "2025-03-31": 1514900000.0,
            "2024-03-31": 82100000.0,
            "2023-03-31": 82300000.0,
            "2022-03-31": 70500000.0,
            "2021-03-31": NaN
        },
        "Capital Expenditure": {
            "2025-03-31": -126000000.0,
            "2024-03-31": -285100000.0,
            "2023-03-31": -486200000.0,
            "2022-03-31": -370100000.0,
            "2021-03-31": NaN
        },
        "Interest Paid Supplemental Data": {
            "2025-03-31": 236200000.0,
            "2024-03-31": 191200000.0,
            "2023-03-31": 181500000.0,
            "2022-03-31": 207800000.0,
            "2021-03-31": NaN
        },
        "Income Tax Paid Supplemental Data": {
            "2025-03-31": 175200000.0,
            "2024-03-31": 517100000.0,
            "2023-03-31": 482600000.0,
            "2022-03-31": 141400000.0,
            "2021-03-31": NaN
        },
        "End Cash Position": {
            "2025-03-31": 771700000.0,
            "2024-03-31": 319700000.0,
            "2023-03-31": 234000000.0,
            "2022-03-31": 317400000.0,
            "2021-03-31": NaN
        },
        "Beginning Cash Position": {
            "2025-03-31": 319700000.0,
            "2024-03-31": 234000000.0,
            "2023-03-31": 317400000.0,
            "2022-03-31": 280000000.0,
            "2021-03-31": NaN
        },
        "Changes In Cash": {
            "2025-03-31": 452000000.0,
            "2024-03-31": 85700000.0,
            "2023-03-31": -83400000.0,
            "2022-03-31": 37400000.0,
            "2021-03-31": NaN
        },
        "Financing Cash Flow": {
            "2025-03-31": -158300000.0,
            "2024-03-31": -2414900000.0,
            "2023-03-31": -3104900000.0,
            "2022-03-31": -2327600000.0,
            "2021-03-31": NaN
        },
        "Cash Flow From Continuing Financing Activities": {
            "2025-03-31": -158300000.0,
            "2024-03-31": -2414900000.0,
            "2023-03-31": -3104900000.0,
            "2022-03-31": -2327600000.0,
            "2021-03-31": NaN
        },
        "Net Other Financing Charges": {
            "2025-03-31": -82900000.0,
            "2024-03-31": -64100000.0,
            "2023-03-31": -75800000.0,
            "2022-03-31": -92700000.0,
            "2021-03-31": NaN
        },
        "Proceeds From Stock Option Exercised": {
            "2025-03-31": -160100000.0,
            "2024-03-31": 0.0,
            "2023-03-31": 0.0,
            "2022-03-31": 0.0,
            "2021-03-31": NaN
        },
        "Cash Dividends Paid": {
            "2025-03-31": -975700000.0,
            "2024-03-31": -911500000.0,
            "2023-03-31": -695300000.0,
            "2022-03-31": -503800000.0,
            "2021-03-31": NaN
        },
        "Net Preferred Stock Issuance": {
            "2025-03-31": 1449500000.0,
            "2024-03-31": 0.0,
            "2023-03-31": 0.0,
            "2022-03-31": NaN,
            "2021-03-31": NaN
        },
        "Preferred Stock Issuance": {
            "2025-03-31": 1449500000.0,
            "2024-03-31": 0.0,
            "2023-03-31": 0.0,
            "2022-03-31": NaN,
            "2021-03-31": NaN
        },
        "Net Common Stock Issuance": {
            "2025-03-31": -31100000.0,
            "2024-03-31": -900000000.0,
            "2023-03-31": -863500000.0,
            "2022-03-31": -355100000.0,
            "2021-03-31": NaN
        },
        "Common Stock Payments": {
            "2025-03-31": -96500000.0,
            "2024-03-31": -982100000.0,
            "2023-03-31": -945800000.0,
            "2022-03-31": -425600000.0,
            "2021-03-31": NaN
        },
        "Common Stock Issuance": {
            "2025-03-31": 65400000.0,
            "2024-03-31": 82100000.0,
            "2023-03-31": 82300000.0,
            "2022-03-31": 70500000.0,
            "2021-03-31": NaN
        },
        "Net Issuance Payments Of Debt": {
            "2025-03-31": -358000000.0,
            "2024-03-31": -539300000.0,
            "2023-03-31": -1470300000.0,
            "2022-03-31": -1376000000.0,
            "2021-03-31": NaN
        },
        "Net Short Term Debt Issuance": {
            "2025-03-31": -1176400000.0,
            "2024-03-31": 1350400000.0,
            "2023-03-31": 0.0,
            "2022-03-31": 0.0,
            "2021-03-31": NaN
        },
        "Short Term Debt Payments": {
            "2025-03-31": -15113900000.0,
            "2024-03-31": -7688700000.0,
            "2023-03-31": 0.0,
            "2022-03-31": 0.0,
            "2021-03-31": NaN
        },
        "Short Term Debt Issuance": {
            "2025-03-31": 13937500000.0,
            "2024-03-31": 9039100000.0,
            "2023-03-31": 0.0,
            "2022-03-31": 0.0,
            "2021-03-31": NaN
        },
        "Net Long Term Debt Issuance": {
            "2025-03-31": 818400000.0,
            "2024-03-31": -1889700000.0,
            "2023-03-31": -1470300000.0,
            "2022-03-31": -1376000000.0,
            "2021-03-31": NaN
        },
        "Long Term Debt Payments": {
            "2025-03-31": -2491800000.0,
            "2024-03-31": -9905400000.0,
            "2023-03-31": -7405300000.0,
            "2022-03-31": -6549000000.0,
            "2021-03-31": NaN
        },
        "Long Term Debt Issuance": {
            "2025-03-31": 3310200000.0,
            "2024-03-31": 8015700000.0,
            "2023-03-31": 5935000000.0,
            "2022-03-31": 5173000000.0,
            "2021-03-31": NaN
        },
        "Investing Cash Flow": {
            "2025-03-31": -287800000.0,
            "2024-03-31": -392100000.0,
            "2023-03-31": -599500000.0,
            "2022-03-31": -477700000.0,
            "2021-03-31": NaN
        },
        "Cash Flow From Continuing Investing Activities": {
            "2025-03-31": -287800000.0,
            "2024-03-31": -392100000.0,
            "2023-03-31": -599500000.0,
            "2022-03-31": -477700000.0,
            "2021-03-31": NaN
        },
        "Net Other Investing Changes": {
            "2025-03-31": -161800000.0,
            "2024-03-31": -107000000.0,
            "2023-03-31": -113300000.0,
            "2022-03-31": -107600000.0,
            "2021-03-31": NaN
        },
        "Net Investment Purchase And Sale": {
            "2025-03-31": NaN,
            "2024-03-31": NaN,
            "2023-03-31": NaN,
            "2022-03-31": 0.0,
            "2021-03-31": 0.0
        },
        "Sale Of Investment": {
            "2025-03-31": NaN,
            "2024-03-31": NaN,
            "2023-03-31": NaN,
            "2022-03-31": 0.0,
            "2021-03-31": 0.0
        },
        "Purchase Of Investment": {
            "2025-03-31": NaN,
            "2024-03-31": NaN,
            "2023-03-31": NaN,
            "2022-03-31": 0.0,
            "2021-03-31": 0.0
        },
        "Net Business Purchase And Sale": {
            "2025-03-31": NaN,
            "2024-03-31": NaN,
            "2023-03-31": NaN,
            "2022-03-31": NaN,
            "2021-03-31": 0.0
        },
        "Purchase Of Business": {
            "2025-03-31": NaN,
            "2024-03-31": NaN,
            "2023-03-31": NaN,
            "2022-03-31": NaN,
            "2021-03-31": 0.0
        },
        "Capital Expenditure Reported": {
            "2025-03-31": -126000000.0,
            "2024-03-31": -285100000.0,
            "2023-03-31": -486200000.0,
            "2022-03-31": -370100000.0,
            "2021-03-31": NaN
        },
        "Operating Cash Flow": {
            "2025-03-31": 898100000.0,
            "2024-03-31": 2892700000.0,
            "2023-03-31": 3621000000.0,
            "2022-03-31": 2842700000.0,
            "2021-03-31": NaN
        },
        "Cash Flow From Continuing Operating Activities": {
            "2025-03-31": 898100000.0,
            "2024-03-31": 2892700000.0,
            "2023-03-31": 3621000000.0,
            "2022-03-31": 2842700000.0,
            "2021-03-31": NaN
        },
        "Change In Working Capital": {
            "2025-03-31": 100100000.0,
            "2024-03-31": -76700000.0,
            "2023-03-31": -16000000.0,
            "2022-03-31": 34200000.0,
            "2021-03-31": NaN
        },
        "Change In Other Working Capital": {
            "2025-03-31": -38100000.0,
            "2024-03-31": -64200000.0,
            "2023-03-31": 404500000.0,
            "2022-03-31": 79400000.0,
            "2021-03-31": NaN
        },
        "Change In Payables And Accrued Expense": {
            "2025-03-31": -347400000.0,
            "2024-03-31": -186900000.0,
            "2023-03-31": 295400000.0,
            "2022-03-31": 207500000.0,
            "2021-03-31": NaN
        },
        "Change In Payable": {
            "2025-03-31": -347400000.0,
            "2024-03-31": -186900000.0,
            "2023-03-31": 295400000.0,
            "2022-03-31": 207500000.0,
            "2021-03-31": NaN
        },
        "Change In Account Payable": {
            "2025-03-31": -345600000.0,
            "2024-03-31": -148400000.0,
            "2023-03-31": 323400000.0,
            "2022-03-31": 192700000.0,
            "2021-03-31": NaN
        },
        "Change In Tax Payable": {
            "2025-03-31": -1800000.0,
            "2024-03-31": -38500000.0,
            "2023-03-31": -28000000.0,
            "2022-03-31": 14800000.0,
            "2021-03-31": NaN
        },
        "Change In Income Tax Payable": {
            "2025-03-31": -1800000.0,
            "2024-03-31": -38500000.0,
            "2023-03-31": -28000000.0,
            "2022-03-31": 14800000.0,
            "2021-03-31": NaN
        },
        "Change In Inventory": {
            "2025-03-31": 31600000.0,
            "2024-03-31": 12800000.0,
            "2023-03-31": -483200000.0,
            "2022-03-31": -177800000.0,
            "2021-03-31": NaN
        },
        "Change In Receivables": {
            "2025-03-31": 454000000.0,
            "2024-03-31": 161600000.0,
            "2023-03-31": -232700000.0,
            "2022-03-31": -74900000.0,
            "2021-03-31": NaN
        },
        "Changes In Account Receivables": {
            "2025-03-31": 454000000.0,
            "2024-03-31": 161600000.0,
            "2023-03-31": -232700000.0,
            "2022-03-31": -74900000.0,
            "2021-03-31": NaN
        },
        "Other Non Cash Items": {
            "2025-03-31": 9600000.0,
            "2024-03-31": 18700000.0,
            "2023-03-31": 14900000.0,
            "2022-03-31": 45000000.0,
            "2021-03-31": NaN
        },
        "Stock Based Compensation": {
            "2025-03-31": 180400000.0,
            "2024-03-31": 177500000.0,
            "2023-03-31": 170400000.0,
            "2022-03-31": 210200000.0,
            "2021-03-31": NaN
        },
        "Asset Impairment Charge": {
            "2025-03-31": 0.0,
            "2024-03-31": 1800000.0,
            "2023-03-31": 1800000.0,
            "2022-03-31": 3000000.0,
            "2021-03-31": NaN
        },
        "Amortization Of Securities": {
            "2025-03-31": NaN,
            "2024-03-31": NaN,
            "2023-03-31": NaN,
            "2022-03-31": NaN,
            "2021-03-31": 0.0
        },
        "Deferred Tax": {
            "2025-03-31": -143300000.0,
            "2024-03-31": -27200000.0,
            "2023-03-31": 205500000.0,
            "2022-03-31": 7900000.0,
            "2021-03-31": NaN
        },
        "Deferred Income Tax": {
            "2025-03-31": -143300000.0,
            "2024-03-31": -27200000.0,
            "2023-03-31": 205500000.0,
            "2022-03-31": 7900000.0,
            "2021-03-31": NaN
        },
        "Depreciation Amortization Depletion": {
            "2025-03-31": 750100000.0,
            "2024-03-31": 879500000.0,
            "2023-03-31": 998400000.0,
            "2022-03-31": 1143500000.0,
            "2021-03-31": NaN
        },
        "Depreciation And Amortization": {
            "2025-03-31": 750100000.0,
            "2024-03-31": 879500000.0,
            "2023-03-31": 998400000.0,
            "2022-03-31": 1143500000.0,
            "2021-03-31": NaN
        },
        "Amortization Cash Flow": {
            "2025-03-31": 584300000.0,
            "2024-03-31": 689100000.0,
            "2023-03-31": 753700000.0,
            "2022-03-31": NaN,
            "2021-03-31": NaN
        },
        "Amortization Of Intangibles": {
            "2025-03-31": 584300000.0,
            "2024-03-31": 689100000.0,
            "2023-03-31": 753700000.0,
            "2022-03-31": NaN,
            "2021-03-31": NaN
        },
        "Depreciation": {
            "2025-03-31": 165800000.0,
            "2024-03-31": 190400000.0,
            "2023-03-31": 244700000.0,
            "2022-03-31": NaN,
            "2021-03-31": NaN
        },
        "Operating Gains Losses": {
            "2025-03-31": 1700000.0,
            "2024-03-31": 12200000.0,
            "2023-03-31": 8300000.0,
            "2022-03-31": 113400000.0,
            "2021-03-31": NaN
        },
        "Earnings Losses From Equity Investments": {
            "2025-03-31": NaN,
            "2024-03-31": NaN,
            "2023-03-31": NaN,
            "2022-03-31": NaN,
            "2021-03-31": 0.0
        },
        "Gain Loss On Investment Securities": {
            "2025-03-31": NaN,
            "2024-03-31": NaN,
            "2023-03-31": NaN,
            "2022-03-31": NaN,
            "2021-03-31": -200000.0
        },
        "Net Income From Continuing Operations": {
            "2025-03-31": -500000.0,
            "2024-03-31": 1906900000.0,
            "2023-03-31": 2237700000.0,
            "2022-03-31": 1285500000.0,
            "2021-03-31": NaN
        }
    }
}